{"per_page":10,"total":1,"current":1,"data":[{"title":"数字图像处理期末","date":"2021-06-09T01:47:16.000Z","date_formatted":{"ll":"Jun 9, 2021","L":"06/09/2021","MM-DD":"06-09"},"excerpt":"<blockquote>\n<p>本笔记主要是服务于广东工业大学（GDUT）数字图像处理期末考试，内涵全部考试范围内的程序</p>\n</blockquote>\n<p>[TOC]</p>\n<h3 id=\"01位图处理程序的最小系统\">01位图处理程序的最小系统<a title=\"#01位图处理程序的最小系统\" href=\"#01位图处理程序的最小系统\"></a></h3>\n<figure class=\"highlight c++\"><table><tr><td class=\"gutter\"><pre><span class=\"line\">1</span><br><span class=\"line\">2</span><br><span class=\"line\">3</span><br><span class=\"line\">4</span><br><span class=\"line\">5</span><br><span class=\"line\">6</span><br><span class=\"line\">7</span><br><span class=\"line\">8</span><br><span class=\"line\">9</span><br><span class=\"line\">10</span><br><span class=\"line\">11</span><br><span class=\"line\">12</span><br><span class=\"line\">13</span><br><span class=\"line\">14</span><br><span class=\"line\">15</span><br><span class=\"line\">16</span><br><span class=\"line\">17</span><br><span class=\"line\">18</span><br><span class=\"line\">19</span><br><span class=\"line\">20</span><br><span class=\"line\">21</span><br><span class=\"line\">22</span><br><span class=\"line\">23</span><br><span class=\"line\">24</span><br><span class=\"line\">25</span><br><span class=\"line\">26</span><br><span class=\"line\">27</span><br><span class=\"line\">28</span><br><span class=\"line\">29</span><br><span class=\"line\">30</span><br><span class=\"line\">31</span><br><span class=\"line\">32</span><br><span class=\"line\">33</span><br><span class=\"line\">34</span><br><span class=\"line\">35</span><br><span class=\"line\">36</span><br><span class=\"line\">37</span><br><span class=\"line\">38</span><br><span class=\"line\">39</span><br><span class=\"line\">40</span><br><span class=\"line\">41</span><br><span class=\"line\">42</span><br><span class=\"line\">43</span><br><span class=\"line\">44</span><br><span class=\"line\">45</span><br><span class=\"line\">46</span><br><span class=\"line\">47</span><br><span class=\"line\">48</span><br><span class=\"line\">49</span><br><span class=\"line\">50</span><br><span class=\"line\">51</span><br><span class=\"line\">52</span><br><span class=\"line\">53</span><br><span class=\"line\">54</span><br><span class=\"line\">55</span><br><span class=\"line\">56</span><br><span class=\"line\">57</span><br><span class=\"line\">58</span><br><span class=\"line\">59</span><br><span class=\"line\">60</span><br><span class=\"line\">61</span><br><span class=\"line\">62</span><br><span class=\"line\">63</span><br><span class=\"line\">64</span><br><span class=\"line\">65</span><br><span class=\"line\">66</span><br><span class=\"line\">67</span><br><span class=\"line\">68</span><br><span class=\"line\">69</span><br><span class=\"line\">70</span><br><span class=\"line\">71</span><br><span class=\"line\">72</span><br><span class=\"line\">73</span><br><span class=\"line\">74</span><br><span class=\"line\">75</span><br><span class=\"line\">76</span><br><span class=\"line\">77</span><br><span class=\"line\">78</span><br><span class=\"line\">79</span><br><span class=\"line\">80</span><br><span class=\"line\">81</span><br><span class=\"line\">82</span><br><span class=\"line\">83</span><br><span class=\"line\">84</span><br><span class=\"line\">85</span><br><span class=\"line\">86</span><br><span class=\"line\">87</span><br><span class=\"line\">88</span><br><span class=\"line\">89</span><br><span class=\"line\">90</span><br><span class=\"line\">91</span><br><span class=\"line\">92</span><br><span class=\"line\">93</span><br><span class=\"line\">94</span><br><span class=\"line\">95</span><br><span class=\"line\">96</span><br><span class=\"line\">97</span><br><span class=\"line\">98</span><br><span class=\"line\">99</span><br><span class=\"line\">100</span><br><span class=\"line\">101</span><br><span class=\"line\">102</span><br><span class=\"line\">103</span><br><span class=\"line\">104</span><br><span class=\"line\">105</span><br><span class=\"line\">106</span><br><span class=\"line\">107</span><br><span class=\"line\">108</span><br><span class=\"line\">109</span><br><span class=\"line\">110</span><br><span class=\"line\">111</span><br><span class=\"line\">112</span><br></pre></td><td class=\"code\"><pre><span class=\"line\"><span class=\"meta\">#<span class=\"meta-keyword\">include</span> <span class=\"meta-string\">&lt;afxwin.h&gt;</span> </span></span><br><span class=\"line\"><span class=\"meta\">#<span class=\"meta-keyword\">include</span> <span class=\"meta-string\">&lt;afxext.h&gt;</span> </span></span><br><span class=\"line\"><span class=\"meta\">#<span class=\"meta-keyword\">include</span> <span class=\"meta-string\">&lt;afxdisp.h&gt;</span>   </span></span><br><span class=\"line\"><span class=\"meta\">#<span class=\"meta-keyword\">include</span> <span class=\"meta-string\">&lt;afxdtctl.h&gt;</span></span></span><br><span class=\"line\"><span class=\"meta\">#<span class=\"meta-keyword\">include</span> <span class=\"meta-string\">&quot;resource.h&quot;</span></span></span><br><span class=\"line\"></span><br><span class=\"line\"><span class=\"comment\">/*文档类*/</span></span><br><span class=\"line\"><span class=\"class\"><span class=\"keyword\">class</span> <span class=\"title\">CDoc</span>:</span> <span class=\"keyword\">public</span> CDocument</span><br><span class=\"line\">&#123;\t</span><br><span class=\"line\">\t<span class=\"built_in\">DECLARE_DYNCREATE</span>(CDoc)</span><br><span class=\"line\">&#125;;</span><br><span class=\"line\"><span class=\"built_in\">IMPLEMENT_DYNCREATE</span>(CDoc, CDocument)</span><br><span class=\"line\"><span class=\"comment\">/*主帧窗口类*/</span></span><br><span class=\"line\"><span class=\"class\"><span class=\"keyword\">class</span> <span class=\"title\">CMainFrame</span> :</span> <span class=\"keyword\">public</span> CFrameWnd</span><br><span class=\"line\">&#123;\t</span><br><span class=\"line\">\t<span class=\"built_in\">DECLARE_DYNCREATE</span>(CMainFrame)</span><br><span class=\"line\">&#125;;</span><br><span class=\"line\"><span class=\"built_in\">IMPLEMENT_DYNCREATE</span>(CMainFrame, CFrameWnd)</span><br><span class=\"line\"></span><br><span class=\"line\"><span class=\"comment\">/*视图类*/</span></span><br><span class=\"line\"><span class=\"class\"><span class=\"keyword\">class</span> <span class=\"title\">CMyView</span> :</span> <span class=\"keyword\">public</span> CView</span><br><span class=\"line\">&#123;</span><br><span class=\"line\"><span class=\"keyword\">public</span>:</span><br><span class=\"line\">\t<span class=\"comment\">//区域一：↓↓↓↓↓↓↓以下区域可自由写代码，其它区域请勿作任何修改↓↓↓↓↓</span></span><br><span class=\"line\"></span><br><span class=\"line\">\t<span class=\"comment\">//↑↑↑↑↑↑↑↑↑↑↑自由写代码区域截止线，其它区域请勿作任何修改↑↑↑↑↑</span></span><br><span class=\"line\">\t<span class=\"built_in\">DECLARE_MESSAGE_MAP</span>()</span><br><span class=\"line\">\t<span class=\"built_in\">DECLARE_DYNCREATE</span>(CMyView)</span><br><span class=\"line\"><span class=\"keyword\">public</span>:</span><br><span class=\"line\">\t<span class=\"built_in\">CMyView</span>()</span><br><span class=\"line\">\t&#123;</span><br><span class=\"line\">\t<span class=\"comment\">//区域二：↓↓↓↓↓↓↓以下区域可自由写代码，其它区域请勿作任何修改↓↓↓↓↓</span></span><br><span class=\"line\"></span><br><span class=\"line\"></span><br><span class=\"line\">\t<span class=\"comment\">//↑↑↑↑↑↑↑↑↑↑↑自由写代码区域截止线，其它区域请勿作任何修改↑↑↑↑↑</span></span><br><span class=\"line\">\t&#125;</span><br><span class=\"line\">\t<span class=\"keyword\">virtual</span> ~<span class=\"built_in\">CMyView</span>()&#123;&#125;</span><br><span class=\"line\"></span><br><span class=\"line\">\t<span class=\"keyword\">public</span>:</span><br><span class=\"line\">\t<span class=\"function\"><span class=\"keyword\">virtual</span> <span class=\"keyword\">void</span> <span class=\"title\">OnDraw</span><span class=\"params\">(CDC* pDC)</span></span>&#123;&#125; </span><br><span class=\"line\"></span><br><span class=\"line\">\t<span class=\"keyword\">protected</span>:                                                          </span><br><span class=\"line\"></span><br><span class=\"line\">\t<span class=\"function\">afx_msg <span class=\"keyword\">void</span> <span class=\"title\">On01</span><span class=\"params\">()</span></span>;                                            </span><br><span class=\"line\"></span><br><span class=\"line\">&#125;;                                                                  </span><br><span class=\"line\"><span class=\"built_in\">IMPLEMENT_DYNCREATE</span>(CMyView, CView)                       </span><br><span class=\"line\"><span class=\"built_in\">BEGIN_MESSAGE_MAP</span>(CMyView, CView)                       </span><br><span class=\"line\">\t</span><br><span class=\"line\">\t<span class=\"built_in\">ON_COMMAND</span>(ID01, On01)                                           </span><br><span class=\"line\">\t</span><br><span class=\"line\"><span class=\"built_in\">END_MESSAGE_MAP</span>()                                                    </span><br><span class=\"line\">                                                                    </span><br><span class=\"line\"><span class=\"comment\">/*应用程序类*/</span>                                                      </span><br><span class=\"line\"><span class=\"class\"><span class=\"keyword\">class</span> <span class=\"title\">CApp</span> :</span> <span class=\"keyword\">public</span> CWinApp&#123;\t<span class=\"function\"><span class=\"keyword\">virtual</span> BOOL <span class=\"title\">InitInstance</span><span class=\"params\">()</span></span>; &#125;;</span><br><span class=\"line\"><span class=\"function\">BOOL <span class=\"title\">CApp::InitInstance</span> <span class=\"params\">()</span>                             </span></span><br><span class=\"line\"><span class=\"function\"></span>&#123;\t\tCSingleDocTemplate* pDocTemplate= <span class=\"keyword\">new</span> <span class=\"built_in\">CSingleDocTemplate</span>(IDR_MENU1,<span class=\"built_in\">RUNTIME_CLASS</span>(CDoc),</span><br><span class=\"line\">\t\t\t\t\t\t\t\t\t\t\t\t\t</span><br><span class=\"line\"></span><br><span class=\"line\"><span class=\"built_in\">RUNTIME_CLASS</span>(CMainFrame),<span class=\"built_in\">RUNTIME_CLASS</span>(CMyView));</span><br><span class=\"line\">\t\t<span class=\"built_in\">AddDocTemplate</span>(pDocTemplate);CCommandLineInfo cmdInfo;<span class=\"built_in\">ParseCommandLine</span>(cmdInfo);</span><br><span class=\"line\">\t\t<span class=\"keyword\">if</span> (!<span class=\"built_in\">ProcessShellCommand</span>(cmdInfo))\t<span class=\"keyword\">return</span> FALSE;            </span><br><span class=\"line\">\t\tm_pMainWnd-&gt;<span class=\"built_in\">ShowWindow</span>(SW_SHOW);m_pMainWnd-&gt;<span class=\"built_in\">UpdateWindow</span>();  </span><br><span class=\"line\">\t\tm_pMainWnd-&gt;<span class=\"built_in\">SetWindowPos</span>(<span class=\"literal\">NULL</span>,<span class=\"number\">0</span>,<span class=\"number\">0</span>,<span class=\"number\">800</span>,<span class=\"number\">600</span>,<span class=\"number\">0</span>);                </span><br><span class=\"line\">\t\tm_pMainWnd-&gt;<span class=\"built_in\">SetWindowText</span>(<span class=\"string\">&quot;版本1.01.&quot;</span>);</span><br><span class=\"line\">\t\t<span class=\"keyword\">return</span> TRUE;                                                 </span><br><span class=\"line\">&#125;                                                                    </span><br><span class=\"line\">CApp theApp;             </span><br><span class=\"line\">                                </span><br><span class=\"line\"><span class=\"comment\">//区域三：↓↓↓↓↓↓↓以下区域可自由写代码，其它区域请勿作任何修改↓↓↓↓↓</span></span><br><span class=\"line\"><span class=\"function\"><span class=\"keyword\">void</span> <span class=\"title\">CMyView::On01</span><span class=\"params\">()</span> </span></span><br><span class=\"line\"><span class=\"function\"></span>&#123;</span><br><span class=\"line\"></span><br><span class=\"line\">\tCBitmap hbitmap;         <span class=\"comment\">//利用&quot;位图类&quot;声明一个标识符为&quot;hbitmap&quot;的变量</span></span><br><span class=\"line\">\tBITMAP bm;               <span class=\"comment\">//利用&quot;位图文件头结构体&quot;声明一个标识符为&quot;bm&quot;的变量</span></span><br><span class=\"line\">    <span class=\"keyword\">unsigned</span> <span class=\"keyword\">char</span> *buffer;            <span class=\"comment\">//声明了一个8位整型数&quot;buffer&quot;指针</span></span><br><span class=\"line\">\t<span class=\"keyword\">int</span> Hang,Lie,WidthBytes;       <span class=\"comment\">//声明行总数目，列总数目，一行象素占据的字节个数</span></span><br><span class=\"line\">    \t\t\t\t\t\t\t<span class=\"comment\">//对于RGB图像而言，一个像素三字节</span></span><br><span class=\"line\"></span><br><span class=\"line\">\thbitmap.<span class=\"built_in\">DeleteObject</span>();                                  <span class=\"comment\">//位图类的清空位图函数</span></span><br><span class=\"line\">\thbitmap.<span class=\"built_in\">LoadBitmap</span> (IDB_BITMAP2);                        <span class=\"comment\">//加载位图文件</span></span><br><span class=\"line\">\thbitmap.<span class=\"built_in\">GetBitmap</span> (&amp;bm);     <span class=\"comment\">//将所加载的位图文件的头文件信息装载到标识符为&quot;bm&quot;的变量中</span></span><br><span class=\"line\">\tHang=bm.bmHeight,Lie=bm.bmWidth,WidthBytes=bm.bmWidthBytes;</span><br><span class=\"line\">    <span class=\"comment\">//值得注意的是unsigned char是一个无符号位的char，可以将其容量看为一个字节（1Byte）或者8bit</span></span><br><span class=\"line\">\tbuffer= <span class=\"keyword\">new</span> <span class=\"keyword\">unsigned</span> <span class=\"keyword\">char</span>[Hang*WidthBytes];    <span class=\"comment\">//buffer指向一个数组，这个数组的大小可以装下该图像的所有字节！！！！！</span></span><br><span class=\"line\">    \t\t\t\t\t\t\t\t\t\t\t<span class=\"comment\">//注意是字节！！！</span></span><br><span class=\"line\">\t<span class=\"comment\">//新开辟一段由上述三个变量决定个数的8位整形数组然后被buffer指针所指向</span></span><br><span class=\"line\">\thbitmap.<span class=\"built_in\">GetBitmapBits</span> (Hang*WidthBytes, buffer);   <span class=\"comment\">//录入buffer数组的位图数据</span></span><br><span class=\"line\"></span><br><span class=\"line\">    <span class=\"comment\">//buffer[j*WidthBytes+i*4+k];</span></span><br><span class=\"line\"></span><br><span class=\"line\">\t<span class=\"keyword\">int</span> i,j;\t<span class=\"comment\">//定义像素坐标变量</span></span><br><span class=\"line\">\t<span class=\"keyword\">int</span> tempR,tempG,tempB;\t<span class=\"comment\">//定义红绿蓝像素数据变量</span></span><br><span class=\"line\"></span><br><span class=\"line\">    CDC *pDC;\t<span class=\"comment\">//定义CDC类的指针变量</span></span><br><span class=\"line\">\tpDC=<span class=\"built_in\">GetDC</span>();\t<span class=\"comment\">//获得当前窗口描述设备对象的指针</span></span><br><span class=\"line\"></span><br><span class=\"line\"> </span><br><span class=\"line\">    <span class=\"keyword\">for</span>(j=<span class=\"number\">0</span>;j&lt;Hang;j++)</span><br><span class=\"line\">\t&#123;</span><br><span class=\"line\">\t\t<span class=\"keyword\">for</span>(i=<span class=\"number\">0</span>;i&lt;Lie;i++)</span><br><span class=\"line\">\t\t&#123;\t</span><br><span class=\"line\">             <span class=\"comment\">//WidthBytes/Lie = 每一个像素的字节数</span></span><br><span class=\"line\">             <span class=\"comment\">//i*(WidthBytes/Lie) = 每个像素字节数的起始索引，由于i在循环中退一位了，所以此时不用-1</span></span><br><span class=\"line\">\t\t\ttempR=buffer[j*WidthBytes+i*WidthBytes/Lie+<span class=\"number\">2</span>];</span><br><span class=\"line\">\t\t\ttempG=buffer[j*WidthBytes+i*WidthBytes/Lie+<span class=\"number\">1</span>];</span><br><span class=\"line\">\t\t\ttempB=buffer[j*WidthBytes+i*WidthBytes/Lie+<span class=\"number\">0</span>];</span><br><span class=\"line\">             <span class=\"comment\">//一次循环读取一次RGB数据送入SetPixel方法生成像素点数据</span></span><br><span class=\"line\">    \t    pDC-&gt;<span class=\"built_in\">SetPixel</span>(i,j,<span class=\"built_in\">RGB</span>(tempR,tempG,tempB));</span><br><span class=\"line\">\t\t&#125;</span><br><span class=\"line\">\t&#125;</span><br><span class=\"line\">&#125;</span><br></pre></td></tr></table></figure>\n<h3 id=\"02-直方图\">02 直方图<a title=\"#02-直方图\" href=\"#02-直方图\"></a></h3>\n<figure class=\"highlight c++\"><table><tr><td class=\"gutter\"><pre><span class=\"line\">1</span><br><span class=\"line\">2</span><br><span class=\"line\">3</span><br><span class=\"line\">4</span><br><span class=\"line\">5</span><br><span class=\"line\">6</span><br><span class=\"line\">7</span><br><span class=\"line\">8</span><br><span class=\"line\">9</span><br><span class=\"line\">10</span><br><span class=\"line\">11</span><br><span class=\"line\">12</span><br><span class=\"line\">13</span><br><span class=\"line\">14</span><br><span class=\"line\">15</span><br><span class=\"line\">16</span><br><span class=\"line\">17</span><br><span class=\"line\">18</span><br><span class=\"line\">19</span><br><span class=\"line\">20</span><br><span class=\"line\">21</span><br><span class=\"line\">22</span><br><span class=\"line\">23</span><br><span class=\"line\">24</span><br><span class=\"line\">25</span><br><span class=\"line\">26</span><br><span class=\"line\">27</span><br><span class=\"line\">28</span><br><span class=\"line\">29</span><br><span class=\"line\">30</span><br><span class=\"line\">31</span><br><span class=\"line\">32</span><br><span class=\"line\">33</span><br><span class=\"line\">34</span><br><span class=\"line\">35</span><br><span class=\"line\">36</span><br><span class=\"line\">37</span><br><span class=\"line\">38</span><br><span class=\"line\">39</span><br><span class=\"line\">40</span><br><span class=\"line\">41</span><br><span class=\"line\">42</span><br><span class=\"line\">43</span><br><span class=\"line\">44</span><br><span class=\"line\">45</span><br><span class=\"line\">46</span><br><span class=\"line\">47</span><br><span class=\"line\">48</span><br><span class=\"line\">49</span><br><span class=\"line\">50</span><br><span class=\"line\">51</span><br><span class=\"line\">52</span><br><span class=\"line\">53</span><br><span class=\"line\">54</span><br><span class=\"line\">55</span><br><span class=\"line\">56</span><br><span class=\"line\">57</span><br><span class=\"line\">58</span><br><span class=\"line\">59</span><br><span class=\"line\">60</span><br><span class=\"line\">61</span><br><span class=\"line\">62</span><br><span class=\"line\">63</span><br><span class=\"line\">64</span><br><span class=\"line\">65</span><br><span class=\"line\">66</span><br><span class=\"line\">67</span><br><span class=\"line\">68</span><br><span class=\"line\">69</span><br><span class=\"line\">70</span><br><span class=\"line\">71</span><br><span class=\"line\">72</span><br><span class=\"line\">73</span><br><span class=\"line\">74</span><br><span class=\"line\">75</span><br><span class=\"line\">76</span><br><span class=\"line\">77</span><br><span class=\"line\">78</span><br><span class=\"line\">79</span><br><span class=\"line\">80</span><br><span class=\"line\">81</span><br><span class=\"line\">82</span><br><span class=\"line\">83</span><br><span class=\"line\">84</span><br><span class=\"line\">85</span><br><span class=\"line\">86</span><br><span class=\"line\">87</span><br><span class=\"line\">88</span><br><span class=\"line\">89</span><br><span class=\"line\">90</span><br><span class=\"line\">91</span><br><span class=\"line\">92</span><br><span class=\"line\">93</span><br><span class=\"line\">94</span><br><span class=\"line\">95</span><br><span class=\"line\">96</span><br><span class=\"line\">97</span><br><span class=\"line\">98</span><br><span class=\"line\">99</span><br><span class=\"line\">100</span><br><span class=\"line\">101</span><br><span class=\"line\">102</span><br><span class=\"line\">103</span><br><span class=\"line\">104</span><br><span class=\"line\">105</span><br><span class=\"line\">106</span><br><span class=\"line\">107</span><br><span class=\"line\">108</span><br><span class=\"line\">109</span><br><span class=\"line\">110</span><br><span class=\"line\">111</span><br><span class=\"line\">112</span><br><span class=\"line\">113</span><br><span class=\"line\">114</span><br><span class=\"line\">115</span><br><span class=\"line\">116</span><br><span class=\"line\">117</span><br><span class=\"line\">118</span><br><span class=\"line\">119</span><br><span class=\"line\">120</span><br><span class=\"line\">121</span><br><span class=\"line\">122</span><br><span class=\"line\">123</span><br><span class=\"line\">124</span><br><span class=\"line\">125</span><br><span class=\"line\">126</span><br><span class=\"line\">127</span><br><span class=\"line\">128</span><br><span class=\"line\">129</span><br><span class=\"line\">130</span><br><span class=\"line\">131</span><br><span class=\"line\">132</span><br><span class=\"line\">133</span><br><span class=\"line\">134</span><br><span class=\"line\">135</span><br><span class=\"line\">136</span><br><span class=\"line\">137</span><br><span class=\"line\">138</span><br><span class=\"line\">139</span><br><span class=\"line\">140</span><br><span class=\"line\">141</span><br><span class=\"line\">142</span><br><span class=\"line\">143</span><br><span class=\"line\">144</span><br><span class=\"line\">145</span><br><span class=\"line\">146</span><br><span class=\"line\">147</span><br><span class=\"line\">148</span><br></pre></td><td class=\"code\"><pre><span class=\"line\"><span class=\"meta\">#<span class=\"meta-keyword\">include</span> <span class=\"meta-string\">&lt;afxwin.h&gt;</span> </span></span><br><span class=\"line\"><span class=\"meta\">#<span class=\"meta-keyword\">include</span> <span class=\"meta-string\">&lt;afxext.h&gt;</span> </span></span><br><span class=\"line\"><span class=\"meta\">#<span class=\"meta-keyword\">include</span> <span class=\"meta-string\">&lt;afxdisp.h&gt;</span>   </span></span><br><span class=\"line\"><span class=\"meta\">#<span class=\"meta-keyword\">include</span> <span class=\"meta-string\">&lt;afxdtctl.h&gt;</span></span></span><br><span class=\"line\"><span class=\"meta\">#<span class=\"meta-keyword\">include</span> <span class=\"meta-string\">&quot;resource.h&quot;</span></span></span><br><span class=\"line\"></span><br><span class=\"line\"><span class=\"comment\">/*文档类*/</span></span><br><span class=\"line\"><span class=\"class\"><span class=\"keyword\">class</span> <span class=\"title\">CDoc</span>:</span> <span class=\"keyword\">public</span> CDocument</span><br><span class=\"line\">&#123;\t</span><br><span class=\"line\">\t<span class=\"built_in\">DECLARE_DYNCREATE</span>(CDoc)</span><br><span class=\"line\">&#125;;</span><br><span class=\"line\"><span class=\"built_in\">IMPLEMENT_DYNCREATE</span>(CDoc, CDocument)</span><br><span class=\"line\"><span class=\"comment\">/*主帧窗口类*/</span></span><br><span class=\"line\"><span class=\"class\"><span class=\"keyword\">class</span> <span class=\"title\">CMainFrame</span> :</span> <span class=\"keyword\">public</span> CFrameWnd</span><br><span class=\"line\">&#123;\t</span><br><span class=\"line\">\t<span class=\"built_in\">DECLARE_DYNCREATE</span>(CMainFrame)</span><br><span class=\"line\">&#125;;</span><br><span class=\"line\"><span class=\"built_in\">IMPLEMENT_DYNCREATE</span>(CMainFrame, CFrameWnd)</span><br><span class=\"line\"></span><br><span class=\"line\"><span class=\"comment\">/*视图类*/</span></span><br><span class=\"line\"><span class=\"class\"><span class=\"keyword\">class</span> <span class=\"title\">CMyView</span> :</span> <span class=\"keyword\">public</span> CView</span><br><span class=\"line\">&#123;</span><br><span class=\"line\"><span class=\"keyword\">public</span>:</span><br><span class=\"line\">\t<span class=\"comment\">//区域一：↓↓↓↓↓↓↓以下区域可自由写代码，其它区域请勿作任何修改↓↓↓↓↓</span></span><br><span class=\"line\"></span><br><span class=\"line\">\t<span class=\"comment\">//↑↑↑↑↑↑↑↑↑↑↑自由写代码区域截止线，其它区域请勿作任何修改↑↑↑↑↑</span></span><br><span class=\"line\">\t<span class=\"built_in\">DECLARE_MESSAGE_MAP</span>()</span><br><span class=\"line\">\t<span class=\"built_in\">DECLARE_DYNCREATE</span>(CMyView)</span><br><span class=\"line\"><span class=\"keyword\">public</span>:</span><br><span class=\"line\">\t<span class=\"built_in\">CMyView</span>()</span><br><span class=\"line\">\t&#123;</span><br><span class=\"line\">\t<span class=\"comment\">//区域二：↓↓↓↓↓↓↓以下区域可自由写代码，其它区域请勿作任何修改↓↓↓↓↓</span></span><br><span class=\"line\"></span><br><span class=\"line\"></span><br><span class=\"line\">\t<span class=\"comment\">//↑↑↑↑↑↑↑↑↑↑↑自由写代码区域截止线，其它区域请勿作任何修改↑↑↑↑↑</span></span><br><span class=\"line\">\t&#125;</span><br><span class=\"line\">\t<span class=\"keyword\">virtual</span> ~<span class=\"built_in\">CMyView</span>()&#123;&#125;</span><br><span class=\"line\">\t<span class=\"keyword\">public</span>:</span><br><span class=\"line\">\t<span class=\"function\"><span class=\"keyword\">virtual</span> <span class=\"keyword\">void</span> <span class=\"title\">OnDraw</span><span class=\"params\">(CDC* pDC)</span></span>&#123;&#125; </span><br><span class=\"line\">\t<span class=\"keyword\">protected</span>:                                                          </span><br><span class=\"line\">\t<span class=\"function\">afx_msg <span class=\"keyword\">void</span> <span class=\"title\">On01</span><span class=\"params\">()</span></span>;                                            </span><br><span class=\"line\">&#125;;                                                                  </span><br><span class=\"line\"><span class=\"built_in\">IMPLEMENT_DYNCREATE</span>(CMyView, CView)                       </span><br><span class=\"line\"><span class=\"built_in\">BEGIN_MESSAGE_MAP</span>(CMyView, CView)                                                  </span><br><span class=\"line\">\t<span class=\"built_in\">ON_COMMAND</span>(ID01, On01)                                           </span><br><span class=\"line\"><span class=\"built_in\">END_MESSAGE_MAP</span>()                                                    </span><br><span class=\"line\">                                                                    </span><br><span class=\"line\"><span class=\"comment\">/*应用程序类*/</span>                                                      </span><br><span class=\"line\"><span class=\"class\"><span class=\"keyword\">class</span> <span class=\"title\">CApp</span> :</span> <span class=\"keyword\">public</span> CWinApp&#123;\t<span class=\"function\"><span class=\"keyword\">virtual</span> BOOL <span class=\"title\">InitInstance</span><span class=\"params\">()</span></span>; &#125;;</span><br><span class=\"line\"><span class=\"function\">BOOL <span class=\"title\">CApp::InitInstance</span> <span class=\"params\">()</span>                             </span></span><br><span class=\"line\"><span class=\"function\"></span>&#123;\t\tCSingleDocTemplate* pDocTemplate= <span class=\"keyword\">new</span> <span class=\"built_in\">CSingleDocTemplate</span>(IDR_MENU1,<span class=\"built_in\">RUNTIME_CLASS</span>(CDoc),</span><br><span class=\"line\">\t\t\t\t\t\t\t\t\t\t\t\t\t</span><br><span class=\"line\"></span><br><span class=\"line\"><span class=\"built_in\">RUNTIME_CLASS</span>(CMainFrame),<span class=\"built_in\">RUNTIME_CLASS</span>(CMyView));</span><br><span class=\"line\">\t\t<span class=\"built_in\">AddDocTemplate</span>(pDocTemplate);CCommandLineInfo cmdInfo;<span class=\"built_in\">ParseCommandLine</span>(cmdInfo);</span><br><span class=\"line\">\t\t<span class=\"keyword\">if</span> (!<span class=\"built_in\">ProcessShellCommand</span>(cmdInfo))\t<span class=\"keyword\">return</span> FALSE;            </span><br><span class=\"line\">\t\tm_pMainWnd-&gt;<span class=\"built_in\">ShowWindow</span>(SW_SHOW);m_pMainWnd-&gt;<span class=\"built_in\">UpdateWindow</span>();  </span><br><span class=\"line\">\t\tm_pMainWnd-&gt;<span class=\"built_in\">SetWindowPos</span>(<span class=\"literal\">NULL</span>,<span class=\"number\">0</span>,<span class=\"number\">0</span>,<span class=\"number\">800</span>,<span class=\"number\">600</span>,<span class=\"number\">0</span>);                </span><br><span class=\"line\">\t\tm_pMainWnd-&gt;<span class=\"built_in\">SetWindowText</span>(<span class=\"string\">&quot;版本1.01.&quot;</span>);</span><br><span class=\"line\">\t\t<span class=\"keyword\">return</span> TRUE;                                                 </span><br><span class=\"line\">&#125;                                                                    </span><br><span class=\"line\">CApp theApp;             </span><br><span class=\"line\">                                </span><br><span class=\"line\"><span class=\"comment\">//区域三：↓↓↓↓↓↓↓以下区域可自由写代码，其它区域请勿作任何修改↓↓↓↓↓</span></span><br><span class=\"line\"><span class=\"function\"><span class=\"keyword\">void</span> <span class=\"title\">CMyView::On01</span><span class=\"params\">()</span> </span></span><br><span class=\"line\"><span class=\"function\"></span>&#123;</span><br><span class=\"line\"></span><br><span class=\"line\">\tCBitmap hbitmap;         <span class=\"comment\">//利用&quot;位图类&quot;声明一个标识符为&quot;hbitmap&quot;的变量</span></span><br><span class=\"line\">\tBITMAP bm;               <span class=\"comment\">//利用&quot;位图文件头结构体&quot;声明一个标识符为&quot;bm&quot;的变量</span></span><br><span class=\"line\">    <span class=\"keyword\">unsigned</span> <span class=\"keyword\">char</span> *buffer;            <span class=\"comment\">//声明了一个8位整型数&quot;buffer&quot;指针</span></span><br><span class=\"line\">\t<span class=\"keyword\">int</span> Hang,Lie,WidthBytes;       <span class=\"comment\">//声明行总数目，列总数目，一行象素占据的字节个数</span></span><br><span class=\"line\"></span><br><span class=\"line\">\thbitmap.<span class=\"built_in\">DeleteObject</span>();                                  <span class=\"comment\">//位图类的清空位图函数</span></span><br><span class=\"line\">\thbitmap.<span class=\"built_in\">LoadBitmap</span> (IDB_BITMAP2);                        <span class=\"comment\">//加载位图文件</span></span><br><span class=\"line\">\thbitmap.<span class=\"built_in\">GetBitmap</span> (&amp;bm);     <span class=\"comment\">//将所加载的位图文件的头文件信息装载到标识符为&quot;bm&quot;的变量中</span></span><br><span class=\"line\">\tHang=bm.bmHeight,Lie=bm.bmWidth,WidthBytes=bm.bmWidthBytes;</span><br><span class=\"line\">\tbuffer= <span class=\"keyword\">new</span> <span class=\"keyword\">unsigned</span> <span class=\"keyword\">char</span>[Hang*WidthBytes]; \t<span class=\"comment\">//buffer指向一个数组，这个数组的大小可以装下该图像的所有字节！！！！！</span></span><br><span class=\"line\">    \t\t\t\t\t\t\t\t\t\t\t<span class=\"comment\">//注意是字节！！！</span></span><br><span class=\"line\">\t<span class=\"comment\">//新开辟一段由上述三个变量决定个数的8位整形数组然后被buffer指针所指向</span></span><br><span class=\"line\">\thbitmap.<span class=\"built_in\">GetBitmapBits</span> (Hang*WidthBytes, buffer);   <span class=\"comment\">//录入buffer数组的位图数据</span></span><br><span class=\"line\"></span><br><span class=\"line\">    <span class=\"comment\">//buffer[j*WidthBytes+i*4+k];</span></span><br><span class=\"line\"></span><br><span class=\"line\">\t<span class=\"keyword\">int</span> i,j;\t\\\\定义像素坐标变量</span><br><span class=\"line\">\t<span class=\"keyword\">int</span> tempR,tempG,tempB;\t\\\\定义红绿蓝像素数据变量</span><br><span class=\"line\"></span><br><span class=\"line\">    CDC *pDC;\t\\\\定义CDC类的指针变量</span><br><span class=\"line\">\tpDC=<span class=\"built_in\">GetDC</span>();\t\\\\获得当前窗口描述设备对象的指针</span><br><span class=\"line\"></span><br><span class=\"line\"></span><br><span class=\"line\">    <span class=\"keyword\">for</span>(j=<span class=\"number\">0</span>;j&lt;Hang;j++)</span><br><span class=\"line\">\t&#123;</span><br><span class=\"line\">\t\t<span class=\"keyword\">for</span>(i=<span class=\"number\">0</span>;i&lt;Lie;i++)</span><br><span class=\"line\">\t\t&#123;</span><br><span class=\"line\">\t\t\ttempR=buffer[j*WidthBytes+i*WidthBytes/Lie+<span class=\"number\">2</span>];</span><br><span class=\"line\">\t\t\ttempG=buffer[j*WidthBytes+i*WidthBytes/Lie+<span class=\"number\">1</span>];</span><br><span class=\"line\">\t\t\ttempB=buffer[j*WidthBytes+i*WidthBytes/Lie+<span class=\"number\">0</span>];</span><br><span class=\"line\">    \t    pDC-&gt;<span class=\"built_in\">SetPixel</span>(i,j,<span class=\"built_in\">RGB</span>(tempR,tempG,tempB));</span><br><span class=\"line\">\t\t&#125;</span><br><span class=\"line\">\t&#125;</span><br><span class=\"line\"></span><br><span class=\"line\">\t<span class=\"built_in\">MessageBox</span>(<span class=\"string\">&quot;以下将RGB图转灰度图&quot;</span>);</span><br><span class=\"line\">\t<span class=\"keyword\">int</span> temp;\t\t\t\t\t\t<span class=\"comment\">//定义整型变量，当前循环到的像素的灰度值会暂时赋值给这个变量</span></span><br><span class=\"line\">    <span class=\"keyword\">unsigned</span> <span class=\"keyword\">char</span> *buffer2;            <span class=\"comment\">//声明了一个8位整型数&quot;buffer&quot;指针，灰度图像的像素灰度数据将会存储在该指针指向的空间</span></span><br><span class=\"line\">\tbuffer2= <span class=\"keyword\">new</span> <span class=\"keyword\">unsigned</span> <span class=\"keyword\">char</span>[Hang*Lie];\t<span class=\"comment\">//因为我们知道这个数组存储的数据是灰度值，灰度值是[0~255],只需要一个字节，因此该</span></span><br><span class=\"line\">    \t\t\t\t\t\t\t\t\t <span class=\"comment\">//数组存储的数据量大小为Hang*Lie*1</span></span><br><span class=\"line\">    <span class=\"keyword\">for</span>(j=<span class=\"number\">0</span>;j&lt;Hang;j++)</span><br><span class=\"line\">\t&#123;</span><br><span class=\"line\">\t\t<span class=\"keyword\">for</span>(i=<span class=\"number\">0</span>;i&lt;Lie;i++)</span><br><span class=\"line\">\t\t&#123;</span><br><span class=\"line\">\t\t\ttempR=buffer[j*WidthBytes+i*WidthBytes/Lie+<span class=\"number\">2</span>];\t<span class=\"comment\">//红[0~255]</span></span><br><span class=\"line\">\t\t\ttempG=buffer[j*WidthBytes+i*WidthBytes/Lie+<span class=\"number\">1</span>];\t<span class=\"comment\">//绿[0~255]</span></span><br><span class=\"line\">\t\t\ttempB=buffer[j*WidthBytes+i*WidthBytes/Lie+<span class=\"number\">0</span>];\t<span class=\"comment\">//蓝[0~255]</span></span><br><span class=\"line\">\t\t\ttemp=(tempR+tempG+tempB)/<span class=\"number\">3</span>;\t\t<span class=\"comment\">//将RGB值相加除以3取平均值</span></span><br><span class=\"line\">    \t    pDC-&gt;<span class=\"built_in\">SetPixel</span>(i,j,<span class=\"built_in\">RGB</span>(temp,temp,temp));\t<span class=\"comment\">//将灰度值作为原来数组的RGB数据传入，因为RGB都是一个值，显示出来的颜色是一个灰色</span></span><br><span class=\"line\">            \t\t\t\t\t\t\t\t\t <span class=\"comment\">//原理参照RGB颜色模型说明</span></span><br><span class=\"line\">\t\t\tbuffer2[j*Lie+i]=temp;\t<span class=\"comment\">// 向buffer这个装灰度图所有数据的数组装入计算好的灰度值</span></span><br><span class=\"line\">\t\t&#125;</span><br><span class=\"line\">\t&#125;</span><br><span class=\"line\"></span><br><span class=\"line\">\t<span class=\"keyword\">int</span> Zhifangtu[<span class=\"number\">256</span>];\t<span class=\"comment\">//众所周知，直方图描述图像中具有该灰度级的像素的个数</span></span><br><span class=\"line\">    <span class=\"keyword\">for</span>(<span class=\"keyword\">int</span> k=<span class=\"number\">0</span>;k&lt;<span class=\"number\">256</span>;k++)</span><br><span class=\"line\">\t\tZhifangtu[k]=<span class=\"number\">0</span>;\t<span class=\"comment\">//先将这个直方图进行初始化，所有的元素赋0，防止数组未赋值的随机数干扰程序</span></span><br><span class=\"line\">\t<span class=\"built_in\">MessageBox</span>(<span class=\"string\">&quot;以下灰度图的直方图输出&quot;</span>);</span><br><span class=\"line\">\t<span class=\"keyword\">for</span>(j=<span class=\"number\">0</span>;j&lt;Hang;j++)</span><br><span class=\"line\">\t&#123;</span><br><span class=\"line\">\t\t<span class=\"keyword\">for</span>(i=<span class=\"number\">0</span>;i&lt;Lie;i++)</span><br><span class=\"line\">\t\t&#123;</span><br><span class=\"line\">\t\t\ttemp=buffer2[j*Lie+i];\t<span class=\"comment\">//存储循环到的像素的灰度值</span></span><br><span class=\"line\">\t\t\tZhifangtu[temp]++;\t<span class=\"comment\">//为相应的灰度级+1</span></span><br><span class=\"line\">\t\t&#125;</span><br><span class=\"line\">\t&#125;</span><br><span class=\"line\">\t</span><br><span class=\"line\">    <span class=\"comment\">//\t以下是简单的图像存储和位图移动</span></span><br><span class=\"line\">\tFILE* fp=<span class=\"built_in\">fopen</span>(<span class=\"string\">&quot;F://abc.txt&quot;</span>,<span class=\"string\">&quot;w&quot;</span>);</span><br><span class=\"line\">\t<span class=\"keyword\">for</span>(k=<span class=\"number\">0</span>;k&lt;<span class=\"number\">256</span>;k++)</span><br><span class=\"line\">\t\t<span class=\"built_in\">fprintf</span>(fp,<span class=\"string\">&quot;灰阶＝%d 次数=%d\\n&quot;</span>,k,Zhifangtu[k]);</span><br><span class=\"line\">\t<span class=\"built_in\">fclose</span>(fp);</span><br><span class=\"line\"></span><br><span class=\"line\">\t<span class=\"keyword\">for</span>(k=<span class=\"number\">0</span>;k&lt;<span class=\"number\">256</span>;k++)</span><br><span class=\"line\">\t&#123;</span><br><span class=\"line\">\t\tpDC-&gt;<span class=\"built_in\">MoveTo</span>(Lie+<span class=\"number\">20</span>+k,Hang);</span><br><span class=\"line\">\t\tpDC-&gt;<span class=\"built_in\">LineTo</span>(Lie+<span class=\"number\">20</span>+k,Hang-Zhifangtu[k]*<span class=\"number\">0.1</span>);</span><br><span class=\"line\">\t&#125;</span><br><span class=\"line\"></span><br><span class=\"line\"></span><br><span class=\"line\"></span><br><span class=\"line\">&#125;</span><br></pre></td></tr></table></figure>\n<h3 id=\"03-点运算\">03 点运算<a title=\"#03-点运算\" href=\"#03-点运算\"></a></h3>\n<figure class=\"highlight c++\"><table><tr><td class=\"gutter\"><pre><span class=\"line\">1</span><br><span class=\"line\">2</span><br><span class=\"line\">3</span><br><span class=\"line\">4</span><br><span class=\"line\">5</span><br><span class=\"line\">6</span><br><span class=\"line\">7</span><br><span class=\"line\">8</span><br><span class=\"line\">9</span><br><span class=\"line\">10</span><br><span class=\"line\">11</span><br><span class=\"line\">12</span><br><span class=\"line\">13</span><br><span class=\"line\">14</span><br><span class=\"line\">15</span><br><span class=\"line\">16</span><br><span class=\"line\">17</span><br><span class=\"line\">18</span><br><span class=\"line\">19</span><br><span class=\"line\">20</span><br><span class=\"line\">21</span><br><span class=\"line\">22</span><br><span class=\"line\">23</span><br><span class=\"line\">24</span><br><span class=\"line\">25</span><br><span class=\"line\">26</span><br><span class=\"line\">27</span><br><span class=\"line\">28</span><br><span class=\"line\">29</span><br><span class=\"line\">30</span><br><span class=\"line\">31</span><br><span class=\"line\">32</span><br><span class=\"line\">33</span><br><span class=\"line\">34</span><br><span class=\"line\">35</span><br><span class=\"line\">36</span><br><span class=\"line\">37</span><br><span class=\"line\">38</span><br><span class=\"line\">39</span><br><span class=\"line\">40</span><br><span class=\"line\">41</span><br><span class=\"line\">42</span><br><span class=\"line\">43</span><br><span class=\"line\">44</span><br><span class=\"line\">45</span><br><span class=\"line\">46</span><br><span class=\"line\">47</span><br><span class=\"line\">48</span><br><span class=\"line\">49</span><br><span class=\"line\">50</span><br><span class=\"line\">51</span><br><span class=\"line\">52</span><br><span class=\"line\">53</span><br><span class=\"line\">54</span><br><span class=\"line\">55</span><br><span class=\"line\">56</span><br><span class=\"line\">57</span><br><span class=\"line\">58</span><br><span class=\"line\">59</span><br><span class=\"line\">60</span><br><span class=\"line\">61</span><br><span class=\"line\">62</span><br><span class=\"line\">63</span><br><span class=\"line\">64</span><br><span class=\"line\">65</span><br><span class=\"line\">66</span><br><span class=\"line\">67</span><br><span class=\"line\">68</span><br><span class=\"line\">69</span><br><span class=\"line\">70</span><br><span class=\"line\">71</span><br><span class=\"line\">72</span><br><span class=\"line\">73</span><br><span class=\"line\">74</span><br><span class=\"line\">75</span><br><span class=\"line\">76</span><br><span class=\"line\">77</span><br><span class=\"line\">78</span><br><span class=\"line\">79</span><br><span class=\"line\">80</span><br><span class=\"line\">81</span><br><span class=\"line\">82</span><br><span class=\"line\">83</span><br><span class=\"line\">84</span><br><span class=\"line\">85</span><br><span class=\"line\">86</span><br><span class=\"line\">87</span><br><span class=\"line\">88</span><br><span class=\"line\">89</span><br><span class=\"line\">90</span><br><span class=\"line\">91</span><br><span class=\"line\">92</span><br><span class=\"line\">93</span><br><span class=\"line\">94</span><br><span class=\"line\">95</span><br><span class=\"line\">96</span><br><span class=\"line\">97</span><br><span class=\"line\">98</span><br><span class=\"line\">99</span><br><span class=\"line\">100</span><br><span class=\"line\">101</span><br><span class=\"line\">102</span><br><span class=\"line\">103</span><br><span class=\"line\">104</span><br><span class=\"line\">105</span><br><span class=\"line\">106</span><br><span class=\"line\">107</span><br><span class=\"line\">108</span><br><span class=\"line\">109</span><br><span class=\"line\">110</span><br><span class=\"line\">111</span><br><span class=\"line\">112</span><br><span class=\"line\">113</span><br><span class=\"line\">114</span><br><span class=\"line\">115</span><br><span class=\"line\">116</span><br><span class=\"line\">117</span><br><span class=\"line\">118</span><br><span class=\"line\">119</span><br><span class=\"line\">120</span><br><span class=\"line\">121</span><br><span class=\"line\">122</span><br><span class=\"line\">123</span><br><span class=\"line\">124</span><br><span class=\"line\">125</span><br><span class=\"line\">126</span><br><span class=\"line\">127</span><br><span class=\"line\">128</span><br><span class=\"line\">129</span><br><span class=\"line\">130</span><br><span class=\"line\">131</span><br><span class=\"line\">132</span><br><span class=\"line\">133</span><br><span class=\"line\">134</span><br><span class=\"line\">135</span><br><span class=\"line\">136</span><br><span class=\"line\">137</span><br><span class=\"line\">138</span><br><span class=\"line\">139</span><br><span class=\"line\">140</span><br><span class=\"line\">141</span><br><span class=\"line\">142</span><br><span class=\"line\">143</span><br><span class=\"line\">144</span><br><span class=\"line\">145</span><br><span class=\"line\">146</span><br><span class=\"line\">147</span><br><span class=\"line\">148</span><br><span class=\"line\">149</span><br><span class=\"line\">150</span><br><span class=\"line\">151</span><br><span class=\"line\">152</span><br><span class=\"line\">153</span><br><span class=\"line\">154</span><br><span class=\"line\">155</span><br><span class=\"line\">156</span><br><span class=\"line\">157</span><br><span class=\"line\">158</span><br><span class=\"line\">159</span><br><span class=\"line\">160</span><br><span class=\"line\">161</span><br><span class=\"line\">162</span><br><span class=\"line\">163</span><br><span class=\"line\">164</span><br><span class=\"line\">165</span><br><span class=\"line\">166</span><br><span class=\"line\">167</span><br><span class=\"line\">168</span><br><span class=\"line\">169</span><br></pre></td><td class=\"code\"><pre><span class=\"line\"><span class=\"meta\">#<span class=\"meta-keyword\">include</span> <span class=\"meta-string\">&lt;afxwin.h&gt;</span> </span></span><br><span class=\"line\"><span class=\"meta\">#<span class=\"meta-keyword\">include</span> <span class=\"meta-string\">&lt;afxext.h&gt;</span> </span></span><br><span class=\"line\"><span class=\"meta\">#<span class=\"meta-keyword\">include</span> <span class=\"meta-string\">&lt;afxdisp.h&gt;</span>   </span></span><br><span class=\"line\"><span class=\"meta\">#<span class=\"meta-keyword\">include</span> <span class=\"meta-string\">&lt;afxdtctl.h&gt;</span></span></span><br><span class=\"line\"><span class=\"meta\">#<span class=\"meta-keyword\">include</span> <span class=\"meta-string\">&quot;resource.h&quot;</span></span></span><br><span class=\"line\"></span><br><span class=\"line\"><span class=\"comment\">/*文档类*/</span></span><br><span class=\"line\"><span class=\"class\"><span class=\"keyword\">class</span> <span class=\"title\">CDoc</span>:</span> <span class=\"keyword\">public</span> CDocument</span><br><span class=\"line\">&#123;\t</span><br><span class=\"line\">\t<span class=\"built_in\">DECLARE_DYNCREATE</span>(CDoc)</span><br><span class=\"line\">&#125;;</span><br><span class=\"line\"><span class=\"built_in\">IMPLEMENT_DYNCREATE</span>(CDoc, CDocument)</span><br><span class=\"line\"><span class=\"comment\">/*主帧窗口类*/</span></span><br><span class=\"line\"><span class=\"class\"><span class=\"keyword\">class</span> <span class=\"title\">CMainFrame</span> :</span> <span class=\"keyword\">public</span> CFrameWnd</span><br><span class=\"line\">&#123;\t</span><br><span class=\"line\">\t<span class=\"built_in\">DECLARE_DYNCREATE</span>(CMainFrame)</span><br><span class=\"line\">&#125;;</span><br><span class=\"line\"><span class=\"built_in\">IMPLEMENT_DYNCREATE</span>(CMainFrame, CFrameWnd)</span><br><span class=\"line\"></span><br><span class=\"line\"><span class=\"comment\">/*视图类*/</span></span><br><span class=\"line\"><span class=\"class\"><span class=\"keyword\">class</span> <span class=\"title\">CMyView</span> :</span> <span class=\"keyword\">public</span> CView</span><br><span class=\"line\">&#123;</span><br><span class=\"line\"><span class=\"keyword\">public</span>:</span><br><span class=\"line\">\t<span class=\"comment\">//区域一：↓↓↓↓↓↓↓以下区域可自由写代码，其它区域请勿作任何修改↓↓↓↓↓</span></span><br><span class=\"line\"></span><br><span class=\"line\">\t<span class=\"comment\">//↑↑↑↑↑↑↑↑↑↑↑自由写代码区域截止线，其它区域请勿作任何修改↑↑↑↑↑</span></span><br><span class=\"line\">\t<span class=\"built_in\">DECLARE_MESSAGE_MAP</span>()</span><br><span class=\"line\">\t<span class=\"built_in\">DECLARE_DYNCREATE</span>(CMyView)</span><br><span class=\"line\"><span class=\"keyword\">public</span>:</span><br><span class=\"line\">\t<span class=\"built_in\">CMyView</span>()</span><br><span class=\"line\">\t&#123;</span><br><span class=\"line\">\t<span class=\"comment\">//区域二：↓↓↓↓↓↓↓以下区域可自由写代码，其它区域请勿作任何修改↓↓↓↓↓</span></span><br><span class=\"line\"></span><br><span class=\"line\"></span><br><span class=\"line\">\t<span class=\"comment\">//↑↑↑↑↑↑↑↑↑↑↑自由写代码区域截止线，其它区域请勿作任何修改↑↑↑↑↑</span></span><br><span class=\"line\">\t&#125;</span><br><span class=\"line\">\t<span class=\"keyword\">virtual</span> ~<span class=\"built_in\">CMyView</span>()&#123;&#125;</span><br><span class=\"line\">\t<span class=\"keyword\">public</span>:</span><br><span class=\"line\">\t<span class=\"function\"><span class=\"keyword\">virtual</span> <span class=\"keyword\">void</span> <span class=\"title\">OnDraw</span><span class=\"params\">(CDC* pDC)</span></span>&#123;&#125; </span><br><span class=\"line\">\t<span class=\"keyword\">protected</span>:                                                          </span><br><span class=\"line\">\t<span class=\"function\">afx_msg <span class=\"keyword\">void</span> <span class=\"title\">On01</span><span class=\"params\">()</span></span>;                                            </span><br><span class=\"line\">&#125;;                                                                  </span><br><span class=\"line\"><span class=\"built_in\">IMPLEMENT_DYNCREATE</span>(CMyView, CView)                       </span><br><span class=\"line\"><span class=\"built_in\">BEGIN_MESSAGE_MAP</span>(CMyView, CView)                                                     </span><br><span class=\"line\">\t<span class=\"built_in\">ON_COMMAND</span>(ID01, On01)                                           </span><br><span class=\"line\"><span class=\"built_in\">END_MESSAGE_MAP</span>()                                                    </span><br><span class=\"line\">                                                                    </span><br><span class=\"line\"><span class=\"comment\">/*应用程序类*/</span>                                                      </span><br><span class=\"line\"><span class=\"class\"><span class=\"keyword\">class</span> <span class=\"title\">CApp</span> :</span> <span class=\"keyword\">public</span> CWinApp&#123;\t<span class=\"function\"><span class=\"keyword\">virtual</span> BOOL <span class=\"title\">InitInstance</span><span class=\"params\">()</span></span>; &#125;;</span><br><span class=\"line\"><span class=\"function\">BOOL <span class=\"title\">CApp::InitInstance</span> <span class=\"params\">()</span>                             </span></span><br><span class=\"line\"><span class=\"function\"></span>&#123;\t\tCSingleDocTemplate* pDocTemplate= <span class=\"keyword\">new</span> <span class=\"built_in\">CSingleDocTemplate</span>(IDR_MENU1,<span class=\"built_in\">RUNTIME_CLASS</span>(CDoc),</span><br><span class=\"line\">\t\t\t\t\t\t\t\t\t\t\t\t\t</span><br><span class=\"line\"></span><br><span class=\"line\"><span class=\"built_in\">RUNTIME_CLASS</span>(CMainFrame),<span class=\"built_in\">RUNTIME_CLASS</span>(CMyView));</span><br><span class=\"line\">\t\t<span class=\"built_in\">AddDocTemplate</span>(pDocTemplate);CCommandLineInfo cmdInfo;<span class=\"built_in\">ParseCommandLine</span>(cmdInfo);</span><br><span class=\"line\">\t\t<span class=\"keyword\">if</span> (!<span class=\"built_in\">ProcessShellCommand</span>(cmdInfo))\t<span class=\"keyword\">return</span> FALSE;            </span><br><span class=\"line\">\t\tm_pMainWnd-&gt;<span class=\"built_in\">ShowWindow</span>(SW_SHOW);m_pMainWnd-&gt;<span class=\"built_in\">UpdateWindow</span>();  </span><br><span class=\"line\">\t\tm_pMainWnd-&gt;<span class=\"built_in\">SetWindowPos</span>(<span class=\"literal\">NULL</span>,<span class=\"number\">0</span>,<span class=\"number\">0</span>,<span class=\"number\">800</span>,<span class=\"number\">600</span>,<span class=\"number\">0</span>);                </span><br><span class=\"line\">\t\tm_pMainWnd-&gt;<span class=\"built_in\">SetWindowText</span>(<span class=\"string\">&quot;版本1.01.&quot;</span>);</span><br><span class=\"line\">\t\t<span class=\"keyword\">return</span> TRUE;                                                 </span><br><span class=\"line\">&#125;                                                                    </span><br><span class=\"line\">CApp theApp;             </span><br><span class=\"line\">                                </span><br><span class=\"line\"><span class=\"comment\">//区域三：↓↓↓↓↓↓↓以下区域可自由写代码，其它区域请勿作任何修改↓↓↓↓↓</span></span><br><span class=\"line\"><span class=\"function\"><span class=\"keyword\">void</span> <span class=\"title\">CMyView::On01</span><span class=\"params\">()</span> </span></span><br><span class=\"line\"><span class=\"function\"></span>&#123;</span><br><span class=\"line\"></span><br><span class=\"line\">\tCBitmap hbitmap;         <span class=\"comment\">//利用&quot;位图类&quot;声明一个标识符为&quot;hbitmap&quot;的变量</span></span><br><span class=\"line\">\tBITMAP bm;               <span class=\"comment\">//利用&quot;位图文件头结构体&quot;声明一个标识符为&quot;bm&quot;的变量</span></span><br><span class=\"line\">    <span class=\"keyword\">unsigned</span> <span class=\"keyword\">char</span> *buffer;            <span class=\"comment\">//声明了一个8位整型数&quot;buffer&quot;指针</span></span><br><span class=\"line\">\t<span class=\"keyword\">int</span> Hang,Lie,WidthBytes;       <span class=\"comment\">//声明行总数目，列总数目，单个象素占据的字节个数</span></span><br><span class=\"line\"></span><br><span class=\"line\">\thbitmap.<span class=\"built_in\">DeleteObject</span>();                                  <span class=\"comment\">//位图类的清空位图函数</span></span><br><span class=\"line\">\thbitmap.<span class=\"built_in\">LoadBitmap</span> (IDB_BITMAP2);                        <span class=\"comment\">//加载位图文件</span></span><br><span class=\"line\">\thbitmap.<span class=\"built_in\">GetBitmap</span> (&amp;bm);     <span class=\"comment\">//将所加载的位图文件的头文件信息装载到标识符为&quot;bm&quot;的变量中</span></span><br><span class=\"line\">\tHang=bm.bmHeight,Lie=bm.bmWidth,WidthBytes=bm.bmWidthBytes;</span><br><span class=\"line\">\tbuffer= <span class=\"keyword\">new</span> <span class=\"keyword\">unsigned</span> <span class=\"keyword\">char</span>[Hang*WidthBytes];    </span><br><span class=\"line\">\t<span class=\"comment\">//新开辟一段由上述三个变量决定个数的8位整形数组然后被buffer指针所指向</span></span><br><span class=\"line\">\thbitmap.<span class=\"built_in\">GetBitmapBits</span> (Hang*WidthBytes, buffer);   <span class=\"comment\">//录入buffer数组的位图数据</span></span><br><span class=\"line\"></span><br><span class=\"line\">    <span class=\"comment\">//buffer[j*WidthBytes+i*4+k];</span></span><br><span class=\"line\"></span><br><span class=\"line\">\t<span class=\"keyword\">int</span> i,j;</span><br><span class=\"line\">\t<span class=\"keyword\">int</span> tempR,tempG,tempB;</span><br><span class=\"line\"></span><br><span class=\"line\">    CDC *pDC;</span><br><span class=\"line\">\tpDC=<span class=\"built_in\">GetDC</span>();</span><br><span class=\"line\"></span><br><span class=\"line\"></span><br><span class=\"line\">    <span class=\"keyword\">for</span>(j=<span class=\"number\">0</span>;j&lt;Hang;j++)</span><br><span class=\"line\">\t&#123;</span><br><span class=\"line\">\t\t<span class=\"keyword\">for</span>(i=<span class=\"number\">0</span>;i&lt;Lie;i++)</span><br><span class=\"line\">\t\t&#123;</span><br><span class=\"line\">\t\t\ttempR=buffer[j*WidthBytes+i*WidthBytes/Lie+<span class=\"number\">2</span>];</span><br><span class=\"line\">\t\t\ttempG=buffer[j*WidthBytes+i*WidthBytes/Lie+<span class=\"number\">1</span>];</span><br><span class=\"line\">\t\t\ttempB=buffer[j*WidthBytes+i*WidthBytes/Lie+<span class=\"number\">0</span>];</span><br><span class=\"line\">    \t    pDC-&gt;<span class=\"built_in\">SetPixel</span>(i,j,<span class=\"built_in\">RGB</span>(tempR,tempG,tempB));</span><br><span class=\"line\">\t\t&#125;</span><br><span class=\"line\">\t&#125;</span><br><span class=\"line\"></span><br><span class=\"line\">\t<span class=\"built_in\">MessageBox</span>(<span class=\"string\">&quot;以下将RGB图转灰度图&quot;</span>);</span><br><span class=\"line\">\t<span class=\"keyword\">int</span> temp;</span><br><span class=\"line\">    <span class=\"keyword\">unsigned</span> <span class=\"keyword\">char</span> *buffer2,*buffer3;            <span class=\"comment\">//声明了一个8位整型数&quot;buffer&quot;指针</span></span><br><span class=\"line\">\tbuffer2= <span class=\"keyword\">new</span> <span class=\"keyword\">unsigned</span> <span class=\"keyword\">char</span>[Hang*Lie];\t   <span class=\"comment\">//存储灰度图字节数据</span></span><br><span class=\"line\">\tbuffer3= <span class=\"keyword\">new</span> <span class=\"keyword\">unsigned</span> <span class=\"keyword\">char</span>[Hang*Lie];\t   <span class=\"comment\">//存储线性点运算处理后的灰度级数据</span></span><br><span class=\"line\">    <span class=\"keyword\">for</span>(j=<span class=\"number\">0</span>;j&lt;Hang;j++)</span><br><span class=\"line\">\t&#123;</span><br><span class=\"line\">\t\t<span class=\"keyword\">for</span>(i=<span class=\"number\">0</span>;i&lt;Lie;i++)</span><br><span class=\"line\">\t\t&#123;</span><br><span class=\"line\">\t\t\ttempR=buffer[j*WidthBytes+i*WidthBytes/Lie+<span class=\"number\">2</span>];</span><br><span class=\"line\">\t\t\ttempG=buffer[j*WidthBytes+i*WidthBytes/Lie+<span class=\"number\">1</span>];</span><br><span class=\"line\">\t\t\ttempB=buffer[j*WidthBytes+i*WidthBytes/Lie+<span class=\"number\">0</span>];</span><br><span class=\"line\">\t\t\ttemp=(tempR+tempG+tempB)/<span class=\"number\">3</span>;</span><br><span class=\"line\">    \t    pDC-&gt;<span class=\"built_in\">SetPixel</span>(i,j,<span class=\"built_in\">RGB</span>(temp,temp,temp));</span><br><span class=\"line\">\t\t\tbuffer2[j*Lie+i]=temp;</span><br><span class=\"line\">\t\t&#125;</span><br><span class=\"line\">\t&#125;</span><br><span class=\"line\">    </span><br><span class=\"line\">    <span class=\"comment\">//结束以上流程后，我们最终得到了存储灰度图数据的buffer2</span></span><br><span class=\"line\"></span><br><span class=\"line\">\t<span class=\"built_in\">MessageBox</span>(<span class=\"string\">&quot;以下灰度图的点运算输出&quot;</span>);</span><br><span class=\"line\"></span><br><span class=\"line\">\t</span><br><span class=\"line\">    <span class=\"comment\">//以下为线性点运算</span></span><br><span class=\"line\">    <span class=\"keyword\">float</span> a=<span class=\"number\">1.5</span>,b=<span class=\"number\">0</span>;\t<span class=\"comment\">//解释一下这个点运算的作用，b=0对整体的图像没有任何影响</span></span><br><span class=\"line\">    \t\t\t\t   <span class=\"comment\">//a&gt;1，即整体图像的对比度增加，亮的地方越亮，暗的地方越暗</span></span><br><span class=\"line\">\t<span class=\"keyword\">int</span> DA,DB;\t\t   <span class=\"comment\">//DA临时存储的是灰度值，DB存储的是计算之后的结果</span></span><br><span class=\"line\">    <span class=\"keyword\">for</span>(j=<span class=\"number\">0</span>;j&lt;Hang;j++)</span><br><span class=\"line\">\t&#123;</span><br><span class=\"line\">\t\t<span class=\"keyword\">for</span>(i=<span class=\"number\">0</span>;i&lt;Lie;i++)</span><br><span class=\"line\">\t\t&#123;</span><br><span class=\"line\">\t\t\tDA=buffer2[j*Lie+i];\t<span class=\"comment\">//将循环到的像素的灰度值存入DA</span></span><br><span class=\"line\">\t\t\tDB=a*DA+b;\t\t\t   <span class=\"comment\">//进行简单的计算工作，对读取到的灰度值进行点运算</span></span><br><span class=\"line\">\t\t\t<span class=\"keyword\">if</span>(DB&gt;<span class=\"number\">255</span>) DB=<span class=\"number\">255</span>;\t    <span class=\"comment\">//一般是不可能大于255的，因为这个灰度值是从前面的RGB图像求平均转化而来的，</span></span><br><span class=\"line\">            \t\t\t\t\t   <span class=\"comment\">//不过为了程序的严谨还是设定将超过255的灰度值设定为255</span></span><br><span class=\"line\">\t\t\t<span class=\"keyword\">if</span>(DB&lt;<span class=\"number\">0</span>) DB=<span class=\"number\">0</span>;\t\t   <span class=\"comment\">//同上面所述也是为了严谨，将小于0的灰度值转化为</span></span><br><span class=\"line\">\t\t\tbuffer3[j*Lie+i]=DB;    <span class=\"comment\">//存储处理后的灰度级</span></span><br><span class=\"line\">\t\t\t</span><br><span class=\"line\">\t\t\ttemp=buffer3[j*Lie+i];\t<span class=\"comment\">//这一步太太冗余了，没必要，使用DB直接代替temp它不香吗</span></span><br><span class=\"line\">            \t\t\t\t\t   <span class=\"comment\">//上面的判断失误了：</span></span><br><span class=\"line\">            \t\t\t\t\t\t\t<span class=\"comment\">//失误在于没有理解buffer是unsigned char类型</span></span><br><span class=\"line\">            \t\t\t\t\t\t\t<span class=\"comment\">//SetPixel是要求输入的RGB数据为整数型</span></span><br><span class=\"line\">\t\t\tpDC-&gt;<span class=\"built_in\">SetPixel</span>(i,j,<span class=\"built_in\">RGB</span>(temp,temp,temp));\t<span class=\"comment\">//将数据加载到位图</span></span><br><span class=\"line\">\t\t&#125;</span><br><span class=\"line\">\t&#125;</span><br><span class=\"line\"><span class=\"comment\">/*</span></span><br><span class=\"line\"><span class=\"comment\">\t //以下为非线性点运算----轮廓线</span></span><br><span class=\"line\"><span class=\"comment\">\tint DA,DB;</span></span><br><span class=\"line\"><span class=\"comment\">    for(j=0;j&lt;Hang;j++)</span></span><br><span class=\"line\"><span class=\"comment\">\t&#123;</span></span><br><span class=\"line\"><span class=\"comment\">\t\tfor(i=0;i&lt;Lie;i++)</span></span><br><span class=\"line\"><span class=\"comment\">\t\t&#123;</span></span><br><span class=\"line\"><span class=\"comment\">\t\t\tDA=buffer2[j*Lie+i];</span></span><br><span class=\"line\"><span class=\"comment\">\t\t\t</span></span><br><span class=\"line\"><span class=\"comment\">\t\t\tif(DA&lt;128)  DB=0;</span></span><br><span class=\"line\"><span class=\"comment\">\t\t\tif(DA&gt;=128&amp;&amp;DA&lt;=128+5) DB=255;</span></span><br><span class=\"line\"><span class=\"comment\">\t\t\tif(DA&gt;128+5) DB=0;</span></span><br><span class=\"line\"><span class=\"comment\"></span></span><br><span class=\"line\"><span class=\"comment\">\t\t\tif(DB&gt;255) DB=255;</span></span><br><span class=\"line\"><span class=\"comment\">\t\t\tif(DB&lt;0) DB=0;</span></span><br><span class=\"line\"><span class=\"comment\">\t\t\tbuffer3[j*Lie+i]=DB;</span></span><br><span class=\"line\"><span class=\"comment\">\t\t\t</span></span><br><span class=\"line\"><span class=\"comment\">\t\t\ttemp=buffer3[j*Lie+i];</span></span><br><span class=\"line\"><span class=\"comment\">\t\t\tpDC-&gt;SetPixel(i,j,RGB(temp,temp,temp));</span></span><br><span class=\"line\"><span class=\"comment\">\t\t&#125;</span></span><br><span class=\"line\"><span class=\"comment\">\t&#125;*/</span></span><br><span class=\"line\"></span><br><span class=\"line\">&#125;</span><br><span class=\"line\"></span><br></pre></td></tr></table></figure>\n<h3 id=\"04-代数运算--加法（生成叠加图像）\">04 代数运算–加法（生成叠加图像）<a title=\"#04-代数运算--加法（生成叠加图像）\" href=\"#04-代数运算--加法（生成叠加图像）\"></a></h3>\n<figure class=\"highlight c++\"><table><tr><td class=\"gutter\"><pre><span class=\"line\">1</span><br><span class=\"line\">2</span><br><span class=\"line\">3</span><br><span class=\"line\">4</span><br><span class=\"line\">5</span><br><span class=\"line\">6</span><br><span class=\"line\">7</span><br><span class=\"line\">8</span><br><span class=\"line\">9</span><br><span class=\"line\">10</span><br><span class=\"line\">11</span><br><span class=\"line\">12</span><br><span class=\"line\">13</span><br><span class=\"line\">14</span><br><span class=\"line\">15</span><br><span class=\"line\">16</span><br><span class=\"line\">17</span><br><span class=\"line\">18</span><br><span class=\"line\">19</span><br><span class=\"line\">20</span><br><span class=\"line\">21</span><br><span class=\"line\">22</span><br><span class=\"line\">23</span><br><span class=\"line\">24</span><br><span class=\"line\">25</span><br><span class=\"line\">26</span><br><span class=\"line\">27</span><br><span class=\"line\">28</span><br><span class=\"line\">29</span><br><span class=\"line\">30</span><br><span class=\"line\">31</span><br><span class=\"line\">32</span><br><span class=\"line\">33</span><br><span class=\"line\">34</span><br><span class=\"line\">35</span><br><span class=\"line\">36</span><br><span class=\"line\">37</span><br><span class=\"line\">38</span><br><span class=\"line\">39</span><br><span class=\"line\">40</span><br><span class=\"line\">41</span><br><span class=\"line\">42</span><br><span class=\"line\">43</span><br><span class=\"line\">44</span><br><span class=\"line\">45</span><br><span class=\"line\">46</span><br><span class=\"line\">47</span><br><span class=\"line\">48</span><br><span class=\"line\">49</span><br><span class=\"line\">50</span><br><span class=\"line\">51</span><br><span class=\"line\">52</span><br><span class=\"line\">53</span><br><span class=\"line\">54</span><br><span class=\"line\">55</span><br><span class=\"line\">56</span><br><span class=\"line\">57</span><br><span class=\"line\">58</span><br><span class=\"line\">59</span><br><span class=\"line\">60</span><br><span class=\"line\">61</span><br><span class=\"line\">62</span><br><span class=\"line\">63</span><br><span class=\"line\">64</span><br><span class=\"line\">65</span><br><span class=\"line\">66</span><br><span class=\"line\">67</span><br><span class=\"line\">68</span><br><span class=\"line\">69</span><br><span class=\"line\">70</span><br><span class=\"line\">71</span><br><span class=\"line\">72</span><br><span class=\"line\">73</span><br><span class=\"line\">74</span><br><span class=\"line\">75</span><br><span class=\"line\">76</span><br><span class=\"line\">77</span><br><span class=\"line\">78</span><br><span class=\"line\">79</span><br><span class=\"line\">80</span><br><span class=\"line\">81</span><br><span class=\"line\">82</span><br><span class=\"line\">83</span><br><span class=\"line\">84</span><br><span class=\"line\">85</span><br><span class=\"line\">86</span><br><span class=\"line\">87</span><br><span class=\"line\">88</span><br><span class=\"line\">89</span><br><span class=\"line\">90</span><br><span class=\"line\">91</span><br><span class=\"line\">92</span><br><span class=\"line\">93</span><br><span class=\"line\">94</span><br><span class=\"line\">95</span><br><span class=\"line\">96</span><br><span class=\"line\">97</span><br><span class=\"line\">98</span><br><span class=\"line\">99</span><br><span class=\"line\">100</span><br><span class=\"line\">101</span><br><span class=\"line\">102</span><br><span class=\"line\">103</span><br><span class=\"line\">104</span><br><span class=\"line\">105</span><br><span class=\"line\">106</span><br><span class=\"line\">107</span><br><span class=\"line\">108</span><br><span class=\"line\">109</span><br><span class=\"line\">110</span><br><span class=\"line\">111</span><br><span class=\"line\">112</span><br><span class=\"line\">113</span><br><span class=\"line\">114</span><br><span class=\"line\">115</span><br><span class=\"line\">116</span><br><span class=\"line\">117</span><br><span class=\"line\">118</span><br><span class=\"line\">119</span><br><span class=\"line\">120</span><br><span class=\"line\">121</span><br><span class=\"line\">122</span><br><span class=\"line\">123</span><br><span class=\"line\">124</span><br><span class=\"line\">125</span><br><span class=\"line\">126</span><br><span class=\"line\">127</span><br><span class=\"line\">128</span><br><span class=\"line\">129</span><br><span class=\"line\">130</span><br><span class=\"line\">131</span><br><span class=\"line\">132</span><br><span class=\"line\">133</span><br><span class=\"line\">134</span><br><span class=\"line\">135</span><br><span class=\"line\">136</span><br><span class=\"line\">137</span><br><span class=\"line\">138</span><br><span class=\"line\">139</span><br><span class=\"line\">140</span><br><span class=\"line\">141</span><br><span class=\"line\">142</span><br><span class=\"line\">143</span><br><span class=\"line\">144</span><br><span class=\"line\">145</span><br><span class=\"line\">146</span><br><span class=\"line\">147</span><br><span class=\"line\">148</span><br><span class=\"line\">149</span><br><span class=\"line\">150</span><br><span class=\"line\">151</span><br><span class=\"line\">152</span><br><span class=\"line\">153</span><br><span class=\"line\">154</span><br><span class=\"line\">155</span><br><span class=\"line\">156</span><br><span class=\"line\">157</span><br><span class=\"line\">158</span><br><span class=\"line\">159</span><br><span class=\"line\">160</span><br><span class=\"line\">161</span><br><span class=\"line\">162</span><br><span class=\"line\">163</span><br><span class=\"line\">164</span><br><span class=\"line\">165</span><br></pre></td><td class=\"code\"><pre><span class=\"line\"><span class=\"meta\">#<span class=\"meta-keyword\">include</span> <span class=\"meta-string\">&lt;afxwin.h&gt;</span> </span></span><br><span class=\"line\"><span class=\"meta\">#<span class=\"meta-keyword\">include</span> <span class=\"meta-string\">&lt;afxext.h&gt;</span> </span></span><br><span class=\"line\"><span class=\"meta\">#<span class=\"meta-keyword\">include</span> <span class=\"meta-string\">&lt;afxdisp.h&gt;</span>   </span></span><br><span class=\"line\"><span class=\"meta\">#<span class=\"meta-keyword\">include</span> <span class=\"meta-string\">&lt;afxdtctl.h&gt;</span></span></span><br><span class=\"line\"><span class=\"meta\">#<span class=\"meta-keyword\">include</span> <span class=\"meta-string\">&quot;resource.h&quot;</span></span></span><br><span class=\"line\"></span><br><span class=\"line\"><span class=\"comment\">/*文档类*/</span></span><br><span class=\"line\"><span class=\"class\"><span class=\"keyword\">class</span> <span class=\"title\">CDoc</span>:</span> <span class=\"keyword\">public</span> CDocument</span><br><span class=\"line\">&#123;\t</span><br><span class=\"line\">\t<span class=\"built_in\">DECLARE_DYNCREATE</span>(CDoc)</span><br><span class=\"line\">&#125;;</span><br><span class=\"line\"><span class=\"built_in\">IMPLEMENT_DYNCREATE</span>(CDoc, CDocument)</span><br><span class=\"line\"><span class=\"comment\">/*主帧窗口类*/</span></span><br><span class=\"line\"><span class=\"class\"><span class=\"keyword\">class</span> <span class=\"title\">CMainFrame</span> :</span> <span class=\"keyword\">public</span> CFrameWnd</span><br><span class=\"line\">&#123;\t</span><br><span class=\"line\">\t<span class=\"built_in\">DECLARE_DYNCREATE</span>(CMainFrame)</span><br><span class=\"line\">&#125;;</span><br><span class=\"line\"><span class=\"built_in\">IMPLEMENT_DYNCREATE</span>(CMainFrame, CFrameWnd)</span><br><span class=\"line\"></span><br><span class=\"line\"><span class=\"comment\">/*视图类*/</span></span><br><span class=\"line\"><span class=\"class\"><span class=\"keyword\">class</span> <span class=\"title\">CMyView</span> :</span> <span class=\"keyword\">public</span> CView</span><br><span class=\"line\">&#123;</span><br><span class=\"line\"><span class=\"keyword\">public</span>:</span><br><span class=\"line\">\t<span class=\"comment\">//区域一：↓↓↓↓↓↓↓以下区域可自由写代码，其它区域请勿作任何修改↓↓↓↓↓</span></span><br><span class=\"line\"></span><br><span class=\"line\">\t<span class=\"comment\">//↑↑↑↑↑↑↑↑↑↑↑自由写代码区域截止线，其它区域请勿作任何修改↑↑↑↑↑</span></span><br><span class=\"line\">\t<span class=\"built_in\">DECLARE_MESSAGE_MAP</span>()</span><br><span class=\"line\">\t<span class=\"built_in\">DECLARE_DYNCREATE</span>(CMyView)</span><br><span class=\"line\"><span class=\"keyword\">public</span>:</span><br><span class=\"line\">\t<span class=\"built_in\">CMyView</span>()</span><br><span class=\"line\">\t&#123;</span><br><span class=\"line\">\t<span class=\"comment\">//区域二：↓↓↓↓↓↓↓以下区域可自由写代码，其它区域请勿作任何修改↓↓↓↓↓</span></span><br><span class=\"line\"></span><br><span class=\"line\"></span><br><span class=\"line\">\t<span class=\"comment\">//↑↑↑↑↑↑↑↑↑↑↑自由写代码区域截止线，其它区域请勿作任何修改↑↑↑↑↑</span></span><br><span class=\"line\">\t&#125;</span><br><span class=\"line\">\t<span class=\"keyword\">virtual</span> ~<span class=\"built_in\">CMyView</span>()&#123;&#125;</span><br><span class=\"line\">\t<span class=\"keyword\">public</span>:</span><br><span class=\"line\">\t<span class=\"function\"><span class=\"keyword\">virtual</span> <span class=\"keyword\">void</span> <span class=\"title\">OnDraw</span><span class=\"params\">(CDC* pDC)</span></span>&#123;&#125; </span><br><span class=\"line\">\t<span class=\"keyword\">protected</span>:                                                          </span><br><span class=\"line\">\t<span class=\"function\">afx_msg <span class=\"keyword\">void</span> <span class=\"title\">On01</span><span class=\"params\">()</span></span>;                                            </span><br><span class=\"line\">&#125;;                                                                  </span><br><span class=\"line\"><span class=\"built_in\">IMPLEMENT_DYNCREATE</span>(CMyView, CView)                       </span><br><span class=\"line\"><span class=\"built_in\">BEGIN_MESSAGE_MAP</span>(CMyView, CView)                                                    </span><br><span class=\"line\">\t<span class=\"built_in\">ON_COMMAND</span>(ID01, On01)                                           </span><br><span class=\"line\"><span class=\"built_in\">END_MESSAGE_MAP</span>()                                                    </span><br><span class=\"line\">                                                                    </span><br><span class=\"line\"><span class=\"comment\">/*应用程序类*/</span>                                                      </span><br><span class=\"line\"><span class=\"class\"><span class=\"keyword\">class</span> <span class=\"title\">CApp</span> :</span> <span class=\"keyword\">public</span> CWinApp&#123;\t<span class=\"function\"><span class=\"keyword\">virtual</span> BOOL <span class=\"title\">InitInstance</span><span class=\"params\">()</span></span>; &#125;;</span><br><span class=\"line\"><span class=\"function\">BOOL <span class=\"title\">CApp::InitInstance</span> <span class=\"params\">()</span>                             </span></span><br><span class=\"line\"><span class=\"function\"></span>&#123;\t\tCSingleDocTemplate* pDocTemplate= <span class=\"keyword\">new</span> <span class=\"built_in\">CSingleDocTemplate</span>(IDR_MENU1,<span class=\"built_in\">RUNTIME_CLASS</span>(CDoc),</span><br><span class=\"line\">\t\t\t\t\t\t\t\t\t\t\t\t\t</span><br><span class=\"line\"></span><br><span class=\"line\"><span class=\"built_in\">RUNTIME_CLASS</span>(CMainFrame),<span class=\"built_in\">RUNTIME_CLASS</span>(CMyView));</span><br><span class=\"line\">\t\t<span class=\"built_in\">AddDocTemplate</span>(pDocTemplate);CCommandLineInfo cmdInfo;<span class=\"built_in\">ParseCommandLine</span>(cmdInfo);</span><br><span class=\"line\">\t\t<span class=\"keyword\">if</span> (!<span class=\"built_in\">ProcessShellCommand</span>(cmdInfo))\t<span class=\"keyword\">return</span> FALSE;            </span><br><span class=\"line\">\t\tm_pMainWnd-&gt;<span class=\"built_in\">ShowWindow</span>(SW_SHOW);m_pMainWnd-&gt;<span class=\"built_in\">UpdateWindow</span>();  </span><br><span class=\"line\">\t\tm_pMainWnd-&gt;<span class=\"built_in\">SetWindowPos</span>(<span class=\"literal\">NULL</span>,<span class=\"number\">0</span>,<span class=\"number\">0</span>,<span class=\"number\">800</span>,<span class=\"number\">600</span>,<span class=\"number\">0</span>);                </span><br><span class=\"line\">\t\tm_pMainWnd-&gt;<span class=\"built_in\">SetWindowText</span>(<span class=\"string\">&quot;版本1.01.&quot;</span>);</span><br><span class=\"line\">\t\t<span class=\"keyword\">return</span> TRUE;                                                 </span><br><span class=\"line\">&#125;                                                                    </span><br><span class=\"line\">CApp theApp;             </span><br><span class=\"line\"></span><br><span class=\"line\"><span class=\"meta\">#<span class=\"meta-keyword\">include</span> <span class=\"meta-string\">&quot;math.h&quot;</span>                                </span></span><br><span class=\"line\"><span class=\"comment\">//区域三：↓↓↓↓↓↓↓以下区域可自由写代码，其它区域请勿作任何修改↓↓↓↓↓</span></span><br><span class=\"line\"><span class=\"function\"><span class=\"keyword\">void</span> <span class=\"title\">CMyView::On01</span><span class=\"params\">()</span> </span></span><br><span class=\"line\"><span class=\"function\"></span>&#123;</span><br><span class=\"line\"></span><br><span class=\"line\">\tCBitmap hbitmap;         <span class=\"comment\">//利用&quot;位图类&quot;声明一个标识符为&quot;hbitmap&quot;的变量</span></span><br><span class=\"line\">\tBITMAP bm;               <span class=\"comment\">//利用&quot;位图文件头结构体&quot;声明一个标识符为&quot;bm&quot;的变量</span></span><br><span class=\"line\">    <span class=\"keyword\">unsigned</span> <span class=\"keyword\">char</span> *buffer;            <span class=\"comment\">//声明了一个8位整型数&quot;buffer&quot;指针</span></span><br><span class=\"line\">\t<span class=\"keyword\">int</span> Hang,Lie,WidthBytes;       <span class=\"comment\">//声明行总数目，列总数目，单个象素占据的字节个数</span></span><br><span class=\"line\"></span><br><span class=\"line\">\thbitmap.<span class=\"built_in\">DeleteObject</span>();                                  <span class=\"comment\">//位图类的清空位图函数</span></span><br><span class=\"line\">\thbitmap.<span class=\"built_in\">LoadBitmap</span> (IDB_BITMAP2);                        <span class=\"comment\">//加载位图文件</span></span><br><span class=\"line\">\thbitmap.<span class=\"built_in\">GetBitmap</span> (&amp;bm);     <span class=\"comment\">//将所加载的位图文件的头文件信息装载到标识符为&quot;bm&quot;的变量中</span></span><br><span class=\"line\">\tHang=bm.bmHeight,Lie=bm.bmWidth,WidthBytes=bm.bmWidthBytes;</span><br><span class=\"line\">\tbuffer= <span class=\"keyword\">new</span> <span class=\"keyword\">unsigned</span> <span class=\"keyword\">char</span>[Hang*WidthBytes];    </span><br><span class=\"line\">\t<span class=\"comment\">//新开辟一段由上述三个变量决定个数的8位整形数组然后被buffer指针所指向</span></span><br><span class=\"line\">\thbitmap.<span class=\"built_in\">GetBitmapBits</span> (Hang*WidthBytes, buffer);   <span class=\"comment\">//录入buffer数组的位图数据</span></span><br><span class=\"line\"></span><br><span class=\"line\">\tCBitmap hbitmap2;         <span class=\"comment\">//利用&quot;位图类&quot;声明一个标识符为&quot;hbitmap&quot;的变量</span></span><br><span class=\"line\">\tBITMAP bm2;               <span class=\"comment\">//利用&quot;位图文件头结构体&quot;声明一个标识符为&quot;bm&quot;的变量</span></span><br><span class=\"line\">    <span class=\"keyword\">unsigned</span> <span class=\"keyword\">char</span> *buffer2,*buffer3;            <span class=\"comment\">//声明了一个8位整型数&quot;buffer&quot;指针</span></span><br><span class=\"line\"></span><br><span class=\"line\">\thbitmap2.<span class=\"built_in\">DeleteObject</span>();                                  <span class=\"comment\">//位图类的清空位图函数</span></span><br><span class=\"line\">\thbitmap2.<span class=\"built_in\">LoadBitmap</span> (IDB_BITMAP3);                        <span class=\"comment\">//加载位图文件</span></span><br><span class=\"line\">\thbitmap2.<span class=\"built_in\">GetBitmap</span> (&amp;bm2);     <span class=\"comment\">//将所加载的位图文件的头文件信息装载到标识符为&quot;bm&quot;的变量中</span></span><br><span class=\"line\">\tbuffer2= <span class=\"keyword\">new</span> <span class=\"keyword\">unsigned</span> <span class=\"keyword\">char</span>[Hang*WidthBytes];    </span><br><span class=\"line\">\t<span class=\"comment\">//新开辟一段由上述三个变量决定个数的8位整形数组然后被buffer指针所指向</span></span><br><span class=\"line\">\thbitmap2.<span class=\"built_in\">GetBitmapBits</span> (Hang*WidthBytes, buffer2);   <span class=\"comment\">//录入buffer数组的位图数据</span></span><br><span class=\"line\"></span><br><span class=\"line\">\tbuffer3= <span class=\"keyword\">new</span> <span class=\"keyword\">unsigned</span> <span class=\"keyword\">char</span>[Hang*WidthBytes];    </span><br><span class=\"line\"></span><br><span class=\"line\"></span><br><span class=\"line\">\t<span class=\"keyword\">int</span> i,j;</span><br><span class=\"line\">\t<span class=\"keyword\">int</span> tempR,tempG,tempB;</span><br><span class=\"line\">\t<span class=\"keyword\">int</span> tempR1,tempG1,tempB1;</span><br><span class=\"line\">\t<span class=\"keyword\">int</span> tempR2,tempG2,tempB2;</span><br><span class=\"line\">\t<span class=\"keyword\">int</span> tempR3,tempG3,tempB3;</span><br><span class=\"line\"></span><br><span class=\"line\">    CDC *pDC;</span><br><span class=\"line\">\tpDC=<span class=\"built_in\">GetDC</span>();</span><br><span class=\"line\"></span><br><span class=\"line\">    <span class=\"keyword\">for</span>(j=<span class=\"number\">0</span>;j&lt;Hang;j++)</span><br><span class=\"line\">\t&#123;</span><br><span class=\"line\">\t\t<span class=\"keyword\">for</span>(i=<span class=\"number\">0</span>;i&lt;Lie;i++)</span><br><span class=\"line\">\t\t&#123;</span><br><span class=\"line\">\t\t\ttempR=buffer[j*WidthBytes+i*WidthBytes/Lie+<span class=\"number\">2</span>];</span><br><span class=\"line\">\t\t\ttempG=buffer[j*WidthBytes+i*WidthBytes/Lie+<span class=\"number\">1</span>];</span><br><span class=\"line\">\t\t\ttempB=buffer[j*WidthBytes+i*WidthBytes/Lie+<span class=\"number\">0</span>];</span><br><span class=\"line\">    \t    pDC-&gt;<span class=\"built_in\">SetPixel</span>(i,j,<span class=\"built_in\">RGB</span>(tempR,tempG,tempB));</span><br><span class=\"line\">\t\t&#125;</span><br><span class=\"line\">\t&#125;</span><br><span class=\"line\"></span><br><span class=\"line\">    <span class=\"keyword\">for</span>(j=<span class=\"number\">0</span>;j&lt;Hang;j++)</span><br><span class=\"line\">\t&#123;</span><br><span class=\"line\">\t\t<span class=\"keyword\">for</span>(i=<span class=\"number\">0</span>;i&lt;Lie;i++)</span><br><span class=\"line\">\t\t&#123;</span><br><span class=\"line\">\t\t\ttempR=buffer2[j*WidthBytes+i*WidthBytes/Lie+<span class=\"number\">2</span>];</span><br><span class=\"line\">\t\t\ttempG=buffer2[j*WidthBytes+i*WidthBytes/Lie+<span class=\"number\">1</span>];</span><br><span class=\"line\">\t\t\ttempB=buffer2[j*WidthBytes+i*WidthBytes/Lie+<span class=\"number\">0</span>];</span><br><span class=\"line\">    \t    pDC-&gt;<span class=\"built_in\">SetPixel</span>(i,j,<span class=\"built_in\">RGB</span>(tempR,tempG,tempB));</span><br><span class=\"line\">\t\t&#125;</span><br><span class=\"line\">\t&#125;</span><br><span class=\"line\">\t</span><br><span class=\"line\">    <span class=\"comment\">//以上代码只是完成了一个功能</span></span><br><span class=\"line\">    <span class=\"comment\">/*</span></span><br><span class=\"line\"><span class=\"comment\">    \t将图像的RGB数据读出来，按顺序放在两个数组中（buffer和buffer2）</span></span><br><span class=\"line\"><span class=\"comment\">    \t其他的就是转化位图操作而已</span></span><br><span class=\"line\"><span class=\"comment\">    */</span></span><br><span class=\"line\">\t<span class=\"comment\">//以下进行代数运算--加法(生成叠加图像)</span></span><br><span class=\"line\">\t<span class=\"built_in\">MessageBox</span>(<span class=\"string\">&quot;以下进行代数运算--加法(生成叠加图像)&quot;</span>);</span><br><span class=\"line\">\t</span><br><span class=\"line\">    <span class=\"keyword\">for</span>(j=<span class=\"number\">0</span>;j&lt;Hang;j++)</span><br><span class=\"line\">\t&#123;</span><br><span class=\"line\">\t\t<span class=\"keyword\">for</span>(i=<span class=\"number\">0</span>;i&lt;Lie;i++)</span><br><span class=\"line\">\t\t&#123;\t</span><br><span class=\"line\">            <span class=\"comment\">/**</span></span><br><span class=\"line\"><span class=\"comment\">            *\t以下代码只是分别将两个数据数组的对应相同位置的像素读取出来，然后求平均</span></span><br><span class=\"line\"><span class=\"comment\">            *\t最后再将数据按顺序存储到buffer3指定的数组中</span></span><br><span class=\"line\"><span class=\"comment\">            */</span></span><br><span class=\"line\">            </span><br><span class=\"line\">\t\t\ttempR1=buffer[j*WidthBytes+i*WidthBytes/Lie+<span class=\"number\">2</span>];</span><br><span class=\"line\">\t\t\ttempG1=buffer[j*WidthBytes+i*WidthBytes/Lie+<span class=\"number\">1</span>];</span><br><span class=\"line\">\t\t\ttempB1=buffer[j*WidthBytes+i*WidthBytes/Lie+<span class=\"number\">0</span>];</span><br><span class=\"line\"></span><br><span class=\"line\">\t\t\ttempR2=buffer2[j*WidthBytes+i*WidthBytes/Lie+<span class=\"number\">2</span>];</span><br><span class=\"line\">\t\t\ttempG2=buffer2[j*WidthBytes+i*WidthBytes/Lie+<span class=\"number\">1</span>];</span><br><span class=\"line\">\t\t\ttempB2=buffer2[j*WidthBytes+i*WidthBytes/Lie+<span class=\"number\">0</span>];</span><br><span class=\"line\"></span><br><span class=\"line\">\t\t\ttempR3=(tempR1+tempR2)/<span class=\"number\">2</span>;</span><br><span class=\"line\">\t\t\ttempG3=(tempG1+tempG2)/<span class=\"number\">2</span>;</span><br><span class=\"line\">\t\t\ttempB3=(tempB1+tempB2)/<span class=\"number\">2</span>;</span><br><span class=\"line\"></span><br><span class=\"line\"></span><br><span class=\"line\">\t\t\tbuffer3[j*WidthBytes+i*WidthBytes/Lie+<span class=\"number\">2</span>]=tempR3;</span><br><span class=\"line\">\t\t\tbuffer3[j*WidthBytes+i*WidthBytes/Lie+<span class=\"number\">1</span>]=tempG3;</span><br><span class=\"line\">\t\t\tbuffer3[j*WidthBytes+i*WidthBytes/Lie+<span class=\"number\">0</span>]=tempB3;</span><br><span class=\"line\">\t\t\tpDC-&gt;<span class=\"built_in\">SetPixel</span>(i,j,<span class=\"built_in\">RGB</span>(tempR3,tempG3,tempB3));</span><br><span class=\"line\">\t\t&#125;</span><br><span class=\"line\">\t&#125;\t<span class=\"comment\">//至此，原图的灰度图生成，放在buffer2内存条中   </span></span><br><span class=\"line\"></span><br><span class=\"line\">&#125;</span><br><span class=\"line\"></span><br></pre></td></tr></table></figure>","link":"2021/06/08/数字图像处理期末","tags":["数字图像处理 C++"],"categories":["课内学习"]},{"title":"MySQL笔记","date":"2021-06-09T01:47:00.000Z","date_formatted":{"ll":"Jun 9, 2021","L":"06/09/2021","MM-DD":"06-09"},"excerpt":"<blockquote>\n<p>本教程为mysql初步笔记，可以简单粗略的将mysql学习一遍</p>\n</blockquote>\n<h3 id=\"第一个部分\">第一个部分<a title=\"#第一个部分\" href=\"#第一个部分\"></a></h3>\n<p>1、sql、DB、DBMS分别是什么，他们之间的关系？</p>\n<pre><code>DB: \n\tDataBase（数据库，数据库实际上在硬盘上以文件的形式存在）\nDBMS: \n\tDataBase Management System（数据库管理系统，常见的有：MySQL Oracle DB2 Sybase SqlServer...）\n\nSQL: \n\t结构化查询语言，是一门标准通用的语言。标准的sql适合于所有的数据库产品。\n\tSQL属于高级语言。只要能看懂英语单词的，写出来的sql语句，可以读懂什么意思。\n\tSQL语句在执行的时候，实际上内部也会先进行编译，然后再执行sql。（sql语句的编译由DBMS完成。）\n\nDBMS负责执行sql语句，通过执行sql语句来操作DB当中的数据。\nDBMS -(执行)-&gt; SQL -(操作)-&gt; DB\n</code></pre>\n<p>2、什么是表？</p>\n<pre><code>表：table\n\n表：table是数据库的基本组成单元，所有的数据都以表格的形式组织，目的是可读性强。\n\n一个表包括行和列：\n\t行：被称为数据/记录(data)\n\t列：被称为字段(column)\n\n学号(int)\t姓名(varchar)\t年龄(int)\n------------------------------------\n110\t\t\t张三\t\t\t\t20\n120\t\t\t李四\t\t\t\t21\n\n每一个字段应该包括哪些属性？\n\t字段名、数据类型、相关的约束。\n</code></pre>\n<p>3、学习MySQL主要还是学习通用的SQL语句，那么SQL语句包括增删改查，SQL语句怎么分类呢？</p>\n<figure class=\"highlight plaintext\"><table><tr><td class=\"gutter\"><pre><span class=\"line\">1</span><br><span class=\"line\">2</span><br><span class=\"line\">3</span><br><span class=\"line\">4</span><br><span class=\"line\">5</span><br></pre></td><td class=\"code\"><pre><span class=\"line\">DQL（数据查询语言）: 查询语句，凡是select语句都是DQL。</span><br><span class=\"line\">DML（数据操作语言）：insert delete update，对表当中的数据进行增删改。</span><br><span class=\"line\">DDL（数据定义语言）：create drop alter，对表结构的增删改。</span><br><span class=\"line\">TCL（事务控制语言）：commit提交事务，rollback回滚事务。(TCL中的T是Transaction)</span><br><span class=\"line\">DCL（数据控制语言）: grant授权、revoke撤销权限等。</span><br></pre></td></tr></table></figure>\n<p>4、导入数据（后期大家练习的时候使用这个演示的数据）</p>\n<figure class=\"highlight plaintext\"><table><tr><td class=\"gutter\"><pre><span class=\"line\">1</span><br><span class=\"line\">2</span><br><span class=\"line\">3</span><br><span class=\"line\">4</span><br><span class=\"line\">5</span><br><span class=\"line\">6</span><br><span class=\"line\">7</span><br><span class=\"line\">8</span><br><span class=\"line\">9</span><br><span class=\"line\">10</span><br><span class=\"line\">11</span><br><span class=\"line\">12</span><br><span class=\"line\">13</span><br></pre></td><td class=\"code\"><pre><span class=\"line\">\t第一步：登录mysql数据库管理系统</span><br><span class=\"line\">\t\tdos命令窗口：</span><br><span class=\"line\">\t\t\tmysql -uroot -p333</span><br><span class=\"line\">\t第二步：查看有哪些数据库</span><br><span class=\"line\">\tshow databases; (这个不是SQL语句，属于MySQL的命令。)</span><br><span class=\"line\">+--------------------+</span><br><span class=\"line\">| Database           |</span><br><span class=\"line\">+--------------------+</span><br><span class=\"line\">| information_schema |</span><br><span class=\"line\">| mysql              |</span><br><span class=\"line\">| performance_schema |</span><br><span class=\"line\">| test               |</span><br><span class=\"line\">+-------------------+\t</span><br></pre></td></tr></table></figure>","link":"2021/06/08/MySQL笔记","tags":["Java Mysql"],"categories":["数据库"]},{"title":"Spring","date":"2021-06-09T01:42:28.000Z","date_formatted":{"ll":"Jun 9, 2021","L":"06/09/2021","MM-DD":"06-09"},"excerpt":"<h2 id=\"1.-spring\">1. Spring<a title=\"#1.-spring\" href=\"#1.-spring\"></a></h2>\n<h3 id=\"1.1-简介\">1.1 简介<a title=\"#1.1-简介\" href=\"#1.1-简介\"></a></h3>\n<ul>\n<li>\n<p>Spring：春天-----&gt; 给软件行业带来了春天!</p>\n</li>\n<li>\n<p>2002,首次推出了Spring框架的雏形：interface21</p>\n</li>\n<li>\n<p>Spring框架即以interface21框架为基础，经过重新设计，并不断丰富其内涵，于2004年3月24日，发布了1.0正式版。</p>\n</li>\n<li>\n<p>Rod Johnson</p>\n</li>\n<li>\n<p>spring理念：使现有的技术更容易使用，本身是一个大杂烩，整合了现有的技术框架</p>\n</li>\n<li>\n<p>SSH：Struct2 + Spring + Hibernate</p>\n</li>\n<li>\n<p>SSM：SpringMVC + Spring + Mybatis</p>\n</li>\n</ul>\n<p>官网：<a href=\"https://docs.spring.io/spring-framework/docs/current/reference/html/overview.html#overview\">https://docs.spring.io/spring-framework/docs/current/reference/html/overview.html#overview</a></p>\n<p>官方下载地址：<a href=\"https://repo.spring.io/libs-release-local/org/springframework/\">https://repo.spring.io/libs-release-local/org/springframework/</a></p>\n<p>Github：<a href=\"https://github.com/spring-projects/spring-framework\">https://github.com/spring-projects/spring-framework</a></p>\n<figure class=\"highlight xml\"><table><tr><td class=\"gutter\"><pre><span class=\"line\">1</span><br><span class=\"line\">2</span><br><span class=\"line\">3</span><br><span class=\"line\">4</span><br><span class=\"line\">5</span><br><span class=\"line\">6</span><br><span class=\"line\">7</span><br><span class=\"line\">8</span><br><span class=\"line\">9</span><br><span class=\"line\">10</span><br><span class=\"line\">11</span><br></pre></td><td class=\"code\"><pre><span class=\"line\"><span class=\"comment\">&lt;!-- https://mvnrepository.com/artifact/org.springframework/spring-webmvc --&gt;</span></span><br><span class=\"line\"><span class=\"tag\">&lt;<span class=\"name\">dependency</span>&gt;</span></span><br><span class=\"line\">    <span class=\"tag\">&lt;<span class=\"name\">groupId</span>&gt;</span>org.springframework<span class=\"tag\">&lt;/<span class=\"name\">groupId</span>&gt;</span></span><br><span class=\"line\">    <span class=\"tag\">&lt;<span class=\"name\">artifactId</span>&gt;</span>spring-webmvc<span class=\"tag\">&lt;/<span class=\"name\">artifactId</span>&gt;</span></span><br><span class=\"line\">    <span class=\"tag\">&lt;<span class=\"name\">version</span>&gt;</span>5.3.7<span class=\"tag\">&lt;/<span class=\"name\">version</span>&gt;</span></span><br><span class=\"line\"><span class=\"tag\">&lt;/<span class=\"name\">dependency</span>&gt;</span></span><br><span class=\"line\"><span class=\"tag\">&lt;<span class=\"name\">dependency</span>&gt;</span></span><br><span class=\"line\">    <span class=\"tag\">&lt;<span class=\"name\">groupId</span>&gt;</span>org.springframework<span class=\"tag\">&lt;/<span class=\"name\">groupId</span>&gt;</span></span><br><span class=\"line\">    <span class=\"tag\">&lt;<span class=\"name\">artifactId</span>&gt;</span>spring-jdbc<span class=\"tag\">&lt;/<span class=\"name\">artifactId</span>&gt;</span></span><br><span class=\"line\">    <span class=\"tag\">&lt;<span class=\"name\">version</span>&gt;</span>5.3.7<span class=\"tag\">&lt;/<span class=\"name\">version</span>&gt;</span></span><br><span class=\"line\"><span class=\"tag\">&lt;/<span class=\"name\">dependency</span>&gt;</span></span><br></pre></td></tr></table></figure>\n<h3 id=\"1.2-优点\">1.2 优点<a title=\"#1.2-优点\" href=\"#1.2-优点\"></a></h3>\n<ul>\n<li>Spring是一个开源的免费的框架（容器）！</li>\n<li>Spring是一个轻量级的，非入侵式的框架！</li>\n<li>控制反转（IOC），面向切面编程（AOP）</li>\n<li>支持事务的处理，对框架整合的支持</li>\n</ul>\n<p>==总结一句话：Spring就是一个轻量级的控制反转（IOC）和面向切面编程（AOP）的框架！==</p>","link":"2021/06/08/Spring","tags":["Spring Java"],"categories":["SSM"]}]}